{
  "version": 1,
  "use_ep": true,
  "compress_rate": 0.65,
  "context_map": {
    "entities": {
      "Gina": {
        "type": "person",
        "count": 19,
        "last_session": 19
      },
      "Jon": {
        "type": "person",
        "count": 19,
        "last_session": 19
      },
      "Door Dash": {
        "type": "org",
        "count": 2,
        "last_session": 6
      },
      "next Friday": {
        "type": "date",
        "count": 1,
        "last_session": 1
      },
      "Finding Freedom": {
        "type": "other",
        "count": 1,
        "last_session": 1
      },
      "regionals": {
        "type": "event",
        "count": 1,
        "last_session": 1
      },
      "local comp": {
        "type": "event",
        "count": 1,
        "last_session": 1
      },
      "dance studio": {
        "type": "other",
        "count": 5,
        "last_session": 18
      },
      "contemporary": {
        "type": "other",
        "count": 1,
        "last_session": 1
      },
      "hip-hop": {
        "type": "other",
        "count": 1,
        "last_session": 1
      },
      "festival next month": {
        "type": "date",
        "count": 1,
        "last_session": 1
      },
      "Paris": {
        "type": "place",
        "count": 1,
        "last_session": 2
      },
      "Rome": {
        "type": "place",
        "count": 2,
        "last_session": 15
      },
      "Marley flooring": {
        "type": "other",
        "count": 1,
        "last_session": 2
      },
      "downtown": {
        "type": "place",
        "count": 1,
        "last_session": 2
      },
      "yesterday": {
        "type": "date",
        "count": 1,
        "last_session": 2
      },
      "dance studio location": {
        "type": "other",
        "count": 1,
        "last_session": 4
      },
      "dance routines": {
        "type": "other",
        "count": 1,
        "last_session": 4
      },
      "upcoming show": {
        "type": "other",
        "count": 1,
        "last_session": 4
      },
      "dance comp": {
        "type": "other",
        "count": 1,
        "last_session": 4
      },
      "next month": {
        "type": "date",
        "count": 2,
        "last_session": 8
      },
      "festival": {
        "type": "other",
        "count": 1,
        "last_session": 5
      },
      "studio": {
        "type": "other",
        "count": 2,
        "last_session": 10
      },
      "online store": {
        "type": "other",
        "count": 2,
        "last_session": 8
      },
      "local artist": {
        "type": "person",
        "count": 1,
        "last_session": 5
      },
      "last week": {
        "type": "date",
        "count": 1,
        "last_session": 6
      },
      "online clothing store": {
        "type": "other",
        "count": 1,
        "last_session": 10
      },
      "interview": {
        "type": "event",
        "count": 1,
        "last_session": 11
      },
      "design internship": {
        "type": "other",
        "count": 1,
        "last_session": 11
      },
      "The Lean Startup": {
        "type": "other",
        "count": 1,
        "last_session": 12
      },
      "store": {
        "type": "other",
        "count": 1,
        "last_session": 16
      },
      "networking events": {
        "type": "other",
        "count": 1,
        "last_session": 16
      },
      "job": {
        "type": "other",
        "count": 1,
        "last_session": 16
      },
      "business": {
        "type": "other",
        "count": 1,
        "last_session": 16
      },
      "plans": {
        "type": "other",
        "count": 1,
        "last_session": 16
      },
      "fashion editors": {
        "type": "org",
        "count": 1,
        "last_session": 17
      },
      "website": {
        "type": "other",
        "count": 1,
        "last_session": 18
      },
      "investors": {
        "type": "other",
        "count": 1,
        "last_session": 18
      },
      "Instagram": {
        "type": "other",
        "count": 1,
        "last_session": 18
      },
      "TikTok": {
        "type": "other",
        "count": 1,
        "last_session": 18
      },
      "Shia Labeouf": {
        "type": "person",
        "count": 1,
        "last_session": 19
      },
      "Friday": {
        "type": "date",
        "count": 1,
        "last_session": 19
      }
    },
    "decisions": [
      "Jon lost his job as a banker",
      "Jon decided to start his own business, a dance studio",
      "Gina lost her job at Door Dash",
      "Jon is starting a dance studio",
      "Jon and Gina decided to plan a dance session next Friday",
      "Gina competed in dance competitions and shows",
      "Jon's dance crew won first place in a local competition last year",
      "Gina's team won first place at regionals at age fifteen",
      "Gina launched an ad campaign for her clothing store",
      "Jon is looking for a spot for his dance studio",
      "Jon considers Marley flooring for his dance studio",
      "Jon is determined to make his passion for dance work",
      "Jon is searching for a place to open his dance studio",
      "Gina emailed wholesalers for her clothing store",
      "One wholesaler replied positively to Gina",
      "Gina is expanding her clothing store",
      "Gina designed a cozy and inviting space for her store",
      "Gina chose stylish and comfortable furniture",
      "Gina's store includes a chandelier for a glam feel",
      "Jon is determined to find the right location for his dance studio",
      "Jon is rehearsing hard for an upcoming show",
      "Jon is preparing for a dance competition next month",
      "Gina found a cool new fashion piece for her store.",
      "Jon had a performance at a festival.",
      "Gina teamed up with a local artist for some cool designs.",
      "Jon aims to turn his dancing passion into a business.",
      "Gina got a tattoo a few years ago that stands for freedom.",
      "Jon is juggling his dance and business goals.",
      "Jon started hitting the gym last week to stay on track with his venture",
      "Gina opened her online clothes store",
      "Gina is passionate about fashion trends and finding unique pieces",
      "Gina wants to blend her love for dance and fashion",
      "Jon lost his job but started his own business",
      "Gina is keeping up with fashion trends for her online clothing store.",
      "Jon is focusing on brand identity and customer relationships for a successful business.",
      "Gina is working on building relationships and creating a strong brand image for her store.",
      "Jon is motivated by seeing his dance studio students succeed.",
      "Gina supports Jon in his journey with his dance studio.",
      "Jon decided to shut down his bank account for his business.",
      "Gina launched new offers and promotions on her online store.",
      "Gina planned to work with fashion bloggers and influencers.",
      "Jon is expanding his dance studio's social media presence.",
      "Jon is hosting a dance competition next month.",
      "Jon decided to turn his love of dance into a business",
      "Jon decided to open a dance studio after losing his job",
      "Jon participated in a fair to show off his studio",
      "Gina started her own online clothing store",
      "Gina is pursuing her own business after losing her job",
      "Jon is focusing on his love for his business to maintain confidence",
      "Jon decided to start his own dance studio after losing his job",
      "Gina attended an interview for a design internship",
      "Gina got accepted for a fashion internship",
      "Gina's internship is a part-time position in the fashion department of an international company",
      "Jon is currently reading 'The Lean Startup'",
      "Jon is wrapping up the business plan and looking for investors",
      "Jon is prepping for his dance studio more than ever",
      "Gina developed a video presentation to teach how to style her fashion pieces",
      "Gina will send her video presentation to Jon later",
      "Jon is offering one-on-one mentoring and training at his dance studio",
      "Jon uses a whiteboard to stay on track, visualize goals, and tokenize successes",
      "Jon color-codes achievements to track progress and stay motivated",
      "Jon was mentored by a business person.",
      "Gina is working on growing the customer base for her online store.",
      "Jon is promoting his business.",
      "Jon is using social media for marketing his dance videos.",
      "Gina opened an online clothing store after losing her job.",
      "Jon is determined not to quit.",
      "Jon is working on opening a dance studio",
      "The grand opening of Jon's dance studio is tomorrow",
      "Gina made a limited edition line last week to show off her style and creativity",
      "Jon chose to go to networking events",
      "Jon is investing time in his business",
      "Jon is writing all his plans down",
      "Gina got noticed by fashion editors and it's been amazing",
      "Jon decided to go full-time with his business idea",
      "Jon started to learn marketing and analytics tools",
      "Jon is excited to guide and mentor aspiring dancers",
      "Gina built a new website for customers to make orders",
      "Jon got a temp job to cover expenses while looking for investors",
      "Jon is sprucing up his business plan and tweaking his pitch to investors",
      "Jon is working on an online platform for the dance studio",
      "Gina offers to help Jon with marketing strategies",
      "Jon and Gina decided to collaborate on content creation and social media management for the dance studio",
      "Jon is working on business plans",
      "Jon is motivated to start a studio for dancers",
      "Gina supports Jon in his endeavor",
      "Jon is committed to welcoming dancers of all ages and backgrounds"
    ],
    "timeline": [
      {
        "time": "next Friday",
        "event": "Jon and Gina plan a dance session"
      },
      {
        "time": "next month",
        "event": "Jon's group performs at a festival"
      },
      {
        "time": "yesterday",
        "event": "Jon visited Paris"
      },
      {
        "time": "N/A",
        "event": "Jon shared that he is searching for a dance studio location"
      },
      {
        "time": "N/A",
        "event": "Jon mentioned rehearsing for an upcoming show"
      },
      {
        "time": "next month",
        "event": "Jon will participate in a dance competition"
      },
      {
        "time": "last week",
        "event": "Jon started hitting the gym"
      },
      {
        "time": "",
        "event": "Gina lost her job at Door Dash"
      },
      {
        "time": "",
        "event": "Gina opened her online clothes store"
      },
      {
        "time": "conversation time",
        "event": "Jon shut down his bank account for his business."
      },
      {
        "time": "conversation time",
        "event": "Gina launched new offers and promotions on her online store."
      },
      {
        "time": "next few months",
        "event": "Gina plans to work with fashion bloggers and influencers."
      },
      {
        "time": "next month",
        "event": "Jon is hosting a dance competition at his studio."
      },
      {
        "time": "conversation time",
        "event": "Jon is expanding his dance studio's social media presence."
      },
      {
        "time": "Yesterday",
        "event": "Jon went to a fair to show off his studio"
      },
      {
        "time": "last week",
        "event": "Jon took a short trip to Rome"
      },
      {
        "time": "tomorrow",
        "event": "Official opening night of Jon's dance studio"
      },
      {
        "time": "last week",
        "event": "Gina made a limited edition line"
      },
      {
        "time": "yesterday",
        "event": "Jon chose to go to networking events"
      },
      {
        "time": "current",
        "event": "Jon is investing time in his business"
      },
      {
        "time": "Last week",
        "event": "Gina got noticed by fashion editors"
      },
      {
        "time": "Today",
        "event": "Jon started to learn marketing and analytics tools"
      },
      {
        "time": "Last week",
        "event": "Gina built a new website for customers to make orders"
      },
      {
        "time": "recently",
        "event": "Jon has been rehearsing hard"
      },
      {
        "time": "last Friday",
        "event": "Gina attended dance class with her friends"
      }
    ],
    "session_counter": 19,
    "token_budget": 300
  },
  "segments": [
    "Gina : Hey Jon! Good to see you. What ' s up? Anything new? Jon : Hey Gina! Good to see you too. Lost my job as a banker yesterday I ' gonna take a shot at starting my own business. Gina : Sorry about your job Jon, starting your own business sounds awesome! Unfortunately lost my job at Door Dash this month. What business are you thinking of? Jon : Sorry to hear that! I ' m starting a dance studio ' cause passionate about dancing great to share it with others. Gina : That ' s cool, Jon! What got you into this biz? Jon : I ' ve been into dancing since was a kid my passion and escape. wanna start a dance studio can teach others joy dancing brings me. Gina : Wow Jon, same here! Dance is my go - to for stress relief. Got any fave styles? Jon : Cool, Gina! love all dances, contemporary is my top pick. expressive and powerful! What ' s your fave? Gina : Yeah, me too! Contemporary dance is expressive and graceful - speaks to me. Jon : Wow, great idea! s go to dance class fun! Gina :! explore new dance moves. plan a dance session soon! Jon :! Wanna see my moves next Fri? Can ' t wait! Gina : Sounds great, Jon! Next Friday works. Let ' s boogie! Jon : excited too! This be great! Gina : Wow! What did you get? Jon : pic ' s from when my dance crew took home first in a local comp last year. amazing up on stage! keen to spread intensity with other peeps. Gina, you ever been in any dance comps or shows? Gina : used to compete in few dance competitions and shows - my fav memory was when my team won first place at a regionals at age fifteenawesome feeling of accomplishment! Jon : Wow! Winning first place amazing! What dance you doing? Gina : Thanks! did contemporary piece called \" Finding Freedom. \" emotional and powerful. Jon : Wow must ' ve been great! Check my ideal dance studio by the water. Gina : Cool setup! Man can ' t deny that view! Got time to rehearse with biz and new store? Jon : Hopefully find a place like this inspire us! Gina : Wow, looks great! What dances you practice? any projects planned? Jon : Thanks! rehearsed with small group of dancers after work. do all kinds of dances, from contemporary to hip-hop. cool projects in works. Finishing up choreography to perform at nearby festival next month. Can ' t wait! Gina : Wow, it looks awesome! Are they yours at festival? They so graceful! Jon : Yeah ones performing at festival! been practicing hard impress with their grace and skill. Gina : Wow, they look great! Can ' t wait to see them rock the festival. Gonna be awesome! Jon : Yeah, awesome! Glad to be part of it.",
    "Gina : Hey Jon! Long time no see! Things hectic lately. launched ad campaign for my clothing store in hopes of growing business. Starting my own store taking risks is scary and rewarding. excited to see where it takes me! Jon : Hey Gina! Whoa your store looks great! All your hard work paid off - congrats! Must be awesome to see your stuff on display. Gina : Thanks a bunch! awesome seeing my vision happen. How ' s the dance studio going? find right spot? Jon : Hey Gina! Thanks for asking. ' on hunt for ideal spot for my dance studio s been quite a journey! been looking at different places picturing how space would look. found a place with great natural light! been to Paris yesterday! sooo cool. Gina : Wow, nice spot! Where is it? Got any other features want to think about before you decide? Paris?! That really great Jon! Never had chance to visit it. Been only to Rome once. Jon : It ' s downtown awesome cuz easy to get to. Plus natural light! Gotta check size & floor quality. need good dance floor with enough bounce for me & students to dance safely. Gina : Definitely! Dance floors help avoid injuries make dancing more enjoyable. thinking about it is great. Any particular type of flooring you like? Jon : good flooring ' s crucial. m after Marley flooring, dance studio s usually use. ' s great ' cause s grippy but still lets you move, plus tough and easy to keep clean. Gina : Sounds great! Marley ' s perfect ; s got right amount of grip and movement. Can ' t wait to see your dance studio done! Jon : can ' t wait to see it done! Looking for the right place getting everything ready mix of exciting and nerve - wracking, but determined to make it work.It ' ll be worth it! Gina : Believe in yourself, Jon! process may be tough you got this. Push through ll be worth it. Don ' t forget to take breaks dance it out when need destress! Jon : Glad I have you in my corner! Gotta make time to dance vent, for sure. ' ll make it through this - hang in there! Gina : Thanks, Jon! Appreciate your support! Jon : Let keep going chase our dreams! Gina : Yeah! ' done so much, nothing but good stuff coming. keep going after our goals making them happen. Jon : Success is almost here. We got this",
    "Jon : Hey Gina, hope you ' re doing ok! Still following my passion for dance. ' s been bumpy, but determined to make it work. still searching for place to open my dance studio. Gina : Hi Jon! happy you re pushing forward with dancing! Inspiring emailed wholesalers one replied said yes today! m over the moon because now can expand my clothing store get closer to customers. Check it out - here ' s a pic! Jon : Wow, Gina! found perfect spot for your store. Way to go, hard work ' s paying off! Gina : Thanks! Glad you like it. great spot. Here ' s a peek at the space I designed. Cozy and inviting - perfect for customers to check out trendy pieces. Jon : Wow it looks great! Must ' ve taken ages to design it. What made pick out furniture and decor? Gina : Thanks! took bit of time wanted to make place look like my own style make customers feel cozy. chose furniture that looks great comfy too. chandelier adds nice glam feel while matching style of store. Jon : Your store looks great - your customers will be so comfy. Gina : Thanks! Making my spot comfortable and inviting for customers is key. want ' em to feel like they ' in cool oasis. creating experience ' ll make ' em come back. Jon : great goal! Creating special experience for customers is key to making them feel welcome and coming back. can create that space ' re imagining. Gina : Thanks. Your support means a lot. sure with hard work and effort, can make special shopping experience for customers. ' s tough but ' m up for the challenge! Jon : always here to support you! Go create something awesome with your store. Keep it up! Gina : Thanks, Jon! I ' ll try my best.You ' re gonna do great with your dance studio keep going stay positive! We ' ll get through this! Jon : Thanks! Your words mean a lot. I staying positive pushing forward. put hearts into our dreams sure we ' ll make it. Gina : Sure thing, Jon! Stay motivated keep going. Hard work pays off eventually. We can do this",
    "Jon : Hey Gina! What ' s up? How ' s the store going? tell you about this thing with my biz. Gina : Hey Jon! The store ' s doing great! a wild ride. How ' s the biz? Jon : Hey Gina! m putting in a lot of work on my business even with obstacles. I ' gonna make it happen! Gina : Wow! You ' ve got drive! Keep it up make a splash. Jon : Thanks Gina! Your help means a lot. Sometimes s hard when things don ' t go my way, but sure if keep pushing, ll reach my dreams! Gina : Understand where you ' re at, Jon. Setbacks are opportunities for comebacks. got skills, passion, drive. Plus my full support. Don ' t give up, buddy! Jon : Thanks! Setbacks can be tough, but with your support, can handle anything. Appreciate you having my back! Gina : ' m here for you no matter what! Anything want to say about your biz? Jon : Searching for a dance studio location tricky determined to find right spot - when sure rest will follow! Gina : Searching for perfect dance studio ' s tough job, Jon. Hang in there ' ll find it soon! Jon : Thanks! Appreciate your encouragement - it means a lot! working on my business and new dance routines - rehearsing hard for an upcoming show. passionate about dancing brings me much joy and fulfillment. Gina : Wow, Jon! You so talented! What show ya got planned? Jon : getting ready for a dance comp near me next month. great chance for to show my skillz get props from dance fam. Super stoked! Gina : Jon, gonna kill it in that competition. Your hard work and talent will pay off! Good luck. Jon : Thanks! Your help means a lot. do my best to make you proud! Gina : No doubt, Jon you ' ve got this.passion commitment awesome! Keep it up! Jon : Thanks! going for my dreams! Gina : Absolutely Jon. always here to cheer you on. Make dreams happen - keep going believe in yourself. You got this! Jon : Thanks, Gina! kind words mean a lot. won ' t give up",
    "Gina : Hey Jon! Great hearing from you again. How have you been? BTW, found a cool new fashion piece for my store. Can ' t wait to share with customers. Jon : Hey Gina! Congrats on new fashion piece! Looks like your store is growing. Remenber the festival I told you about? Had that performance awesome - many people there complementing my dance moves. Dancing brings me joy nice to be reminded why I ' m passionate about it. Gina : Wow! looks great. look badass on stage. BTW, ' s your favorite part of running your own studio? Jon : Thanks, Gina! I love running my own studio. s great having freedom to create space help dancers of all ages and levels express themselves. super thrilled about dancing each day seeing students progress. fulfilling. Gina : That ' s awesome! sure feel great knowing your students are doing so well with dance. s amazing what it can do for people! btw - been working hard on my online store teamed up with a local artist for cool designs. Check ' em out! Jon : It looks awesome. Your commitment and creativity in your business stands out. How ' you come up with these cool designs? Gina : Thanks Jon! got idea from a fashion mag saw there wasn ' t much around like it. worked with the artist to make it happen - s about being ahead of the game giving customers something different. Jon : Nice one, Gina! never shy away from challenge always try something new. impressed by your willingness to take risks - inspiring. Gina : Thanks! Taking risks is scary but only way to grow, right? part of journey to success. Jon : agree - taking risks is key for success. ' s made me grow, got me out of my secure 9 - 5 as a banker. Now aiming to turn my dancing passion into a business.determined to make it work, just know it! said, don ' t underestimate difficulties - it ain ' t been a walk in the park, ' s for sure. Gina : tough starting a biz, but don ' t let it get you down. can make your studio work, sure. remember, always here for you. Jon : Thanks, Gina. Your help means a lot. ' ll keep plugging away stay optimistic. Gina : quote kept me positive through tough times. need a push sometimes, right? Even made a tattoo to remind myself about. Jon : Love the tattoo, you get it? Gina : Thanks! Got tattoo few years ago stands for freedom - dancing without worrying what people think. reminder to follow my passions express myself. Jon : Nice reminder, Gina! important to have freedom express ourselves without worry. Dance gives me escape to be myself. Gina : Totally agree, Jon. Dancing lets us be ourselves ain ' t nothing like feeling it gives us. dedicated to your studio, ' s inspiring. Chase those dreams, buddy! Jon : Thanks, Gina! Your support means so much. gonna keep chasing after dreams. Dance is my passion, keep working hard to make it success! Gina : right attitude! juggling dance and business goals? Jon : Thanks! Juggling both my passions can be tricky, but rewarding. Dancing and running my biz need hard work, plus they give me energy for each other. dance moves get me pumped to tackle business goals, successes there boost my drive to keep dreaming on dance floor. balancing act, but fun. Gina : Wow, Jon! amazing at juggling both your passions. Finding happy medium is key - keep going don ' t stop dreaming, buddy! Jon : Thanks, Gina! Your pep - talk really meant a lot' not gonna give up on dreams - dance studio biz ventures need hard work putting in. Love having you in my corner thanks for always being there! Gina : Yeah Jon, I ' m here for you! Chasing dreams helping each other out. Let ' s keep movin ' forward",
    "Jon : Hi Gina! Been hectic for me lately. Started hitting gym last week to stay on track with venture. Gotta figure out how to balance it all, but it ' s going well. How about you? Gina : Hey Jon! Great to hear from you. Been having tough times lately. Jon : Oof, sorry to hear that. What ' s up? anything I can do to help? Gina : Thanks, Jon! Appreciate your offer. Since lost my job at Door Dash, things tough. here ' s good news - got something to share! Jon : Wow ' s awesome! Can ' t wait to hear it! Gina : My online clothes store is open! been dreaming of this for a while now - can ' t wait to see what happens! Jon : Congrats! That ' s awesome! What gave you idea to start the online store? Gina : Thanks! passionate about fashion trends finding unique pieces. wanted to blend my love for dance and fashion, perfect match. Jon : Wow awesome! Combining two interests into store is super cool. Best of luck with it! Gina : Thanks! How is biz going? hope it ' s going well! Jon : Thanks for askin ', Gina! Losing my job was hard, livin ' my dreams now. Startin ' my biz tough but ' gonna make it! keep facing new challenges, sure ' ll be worth it in the end. Gina : starting and running my own biz had ups and downs - amazing ride! Jon : a rollercoaster. your success inspires me to keep pushing forward. Your determination is awesome! Gina : Thanks, Jon! Your words encouraging. Glad my journey is inspiring others.Jon : Yeah, totally! It ' s great we both face same challenges motivates us like having a partner to dance with! Gina : Yep! We re both on different paths nice to have someone to root for us. We can do it! Jon : Definitely! Having someone back us up is great. Let ' s keep going reach success together! Gina : keep chasing our dreams supporting each other celebrating achievements. can do great things together! Jon : Yeah, Gina, thanks for having my back. Here ' s to taking on new heights all trials come with it. Cheers",
    "Jon : Hey Gina, how ' s it going? Gina : Hey Jon, my online clothing store a roller coaster rewarding. Starting a business takes courage - you hang in there too! Jon : Thanks Gina! s been tough, but I ' m gonna make it happen. s been great! you ' re awesome with your store. How ' s it going? Gina : Thanks! Appreciate your kind words. Store ' s going good, keeping up with fashion trends can offer best pieces to customers. been a lot of work, enjoying it. any advice or tips on running a successful biz? Jon : brand identity is key. Make sure yours stands out. to build relationships with your customers let them know you care. don ' t forget to stay positive motivate others. Your energy contagious! Gina : Thanks for advice, Jon! Building relationships creating strong brand image for my store always working on. right staying positive is key. helps you stay motivated with your dance studio business? Jon : students succeed motivates me. awesome to help them learn reach goals. Your support, Gina, means a lot too. photo of us after during one dance clases. Gina : awesome, Jon! students grow succeed must be fulfilling. Glad I can be part of this journey! Jon : Thanks for being there for me! made a huge difference feels great. Gina : Glad I could help, Jon! nice to be part of something positive. Supporting your dreams is awesome! Jon : Thanks for being there for me. Your help means a lot. Gina : ' m here for you, rooting for you all the. Jon : Thanks, grateful for your help with staying motivated. Gina : Glad to cheer you on. Keep going never give up! Jon : Thanks, Gina! won ' t quit - your words motivate me to keep going! Gina : Believe in yourselfEven when it ' s tough you got this! Keep going! Jon : I gonna keep believing in myself. Thanks for kind words",
    "Jon : Hey Gina, had to shut down my bank account. It was tough, but needed to do it for my biz. Gina : Oh no, Jon! Sorry to hear that. Tough decision for you? How ' re you handling changes? Jon : tough call, but thought it ' d help my biz grow. Handling changes hard, but staying positive looking ahead. Anything new for you? Gina : Oof, ' s tough, Jon. got new offers and promotions going on my online store to bring in new customers. s been wild ride starting my business, not giving up! Jon : Nice one, Gina! Love how you never give up. What helps you stay motivated? Gina : Thanks Jon! Dance is my stress relief and fashion fuels my creativity. love finding new trends for my store. keeps me motivated to keep growing. Check out this pic of fave dance session! Jon : Wow, s great! What made combine clothing biz and dance? Gina : Thanks! passionate about dance and fashion combining them lets me show creativity share my love with others. Plus can add dance - inspired items to my store! Jon : Nice work! Combining passions is always cool. How ' s it going? Gina : Thanks! good - customers love new offers and promotions seeing more sales. People to like my designs, always on hunt for unique, trendy pieces. Growing my customer base is main focus now. Jon : Sounds like all your effort ' s paying off. Anything planned to grow your customer base? Gina : Yeah have few plans. thinking of working with fashion bloggers and influencers in next few months to get more attention for my store. Plus going to do more ads can reach more people. focused on building my customer base and making my store a top destination for fashion fans.awesome to see it all coming together! You, Jon? What do you have going for your dance studio? Jon : Thanks, Gina! expanding my dance studio ' s social media presence offering workshops classes to local schools and centers hosting a dance comp etition next month to showcase local talent bring more attention to my studio. work ' s paying off - seeing progress dancers excited. great feeling to give a place where people can express themselves through dance! Gina : Wow! fantastic your studio ' s expanding giving dancers an outlet. proud of progress you made - keep it up! Jon : Thanks! Your backing means a lot. trying to make my plan work, tough. Your encouragement helps. you coming to the event next month? Love to have you there! Gina : Woah, cool event! What ' s gonna be happening? love to join in show my support! Jon : Thanks, Gina! My dance studio and some other schools bringing best moves for awesome night of performances and judging. super creative and fun. Come join us! Gina : Sounds great! definitely in for the show. Jon : Cool! Can ' t wait to see you! Gina : Thanks, Jon! See you at the event! Jon : Gina, good luck with your store! Gina : Thanks, Jon! Appreciate kind words. < 3 Jon : Sure, I am always there for you! Gina : Thanks! Your support means a lot. keep pursuing my goals hope you do too! Jon : Thanks! won ' t quit on my dreams. Your words motivate me. Bye! Gina : Bye Jon! You got this! Believe in yourself and keep pushing. Take care",
    "Jon : Hey Gina! I turning my loves of dance into a business. sunk tons of time into studio lately, look at students - they ' re already killing it. learning with them! Gina : Hey Jon! Wow, way to take your passion make it into a biz! dance studio looks awesome. Jon : Thanks, Gina! determined to make this studio work. Losing my job was tough but gave me push I needed to do what I love. Gina : Woah, Jon! Tough times can be gateway to awesome things. Glad you worked up courage to go after your dreams! Jon : Yeah, Gina! s been tough, living my true self. Dancing makes me happy, now to share that with other people. Seeing students get better brings me such joy. Gina : Wow Jon, you look happy when you dance! Show world your true self keep dancing! Jon : Thanks a bunch, Gina! You seriously rock. Dancing for me is like way to express myself find my happy place. used to be scared to death of what people think, but learnt my own happiness is most important thing. been tough but also best thing ever! Gina : remember those dance classes! used to love spending time in studio. photo looks awesome, brings back lots of memories. nice to know, dance is still your happy place. Jon : Nice, Gina! happy dance has special meaning to both of us. cool way to express ourselves. loved taking lessons with friends when younger. memories are precious. glad can still enjoy it with my own studio. Thanks for always being there for me. Gina : Hey Jon! Got your back - dance is awesome for expressing yourself finding happiness. Here ' s one of my trophies from dance contest, nice reminder of hard work, dedication and joy it brings. Jon : Wow! It looks awesome! Thanks for the support, means a lot.Gina : No prob, Jon! earned kudos for hard work Keep it up! Jon : Thanks! keep pushing working hard Won ' t let anything hold me back! Gina : Way to go, Jon! Keep it up you ' re almost there",
    "Jon : Hi Gina! wanted to fill you in on my business. Yesterday, went to a fair to show off my studio, both stressful and great! got possible leads, awesome. overall learned this biz is no cakewalk having confidence in yourself important for making it successful! Gina : Hey Jon, congrats on the fair! awesome to see your hard work paying off. Keep on pushing, pal, you headed for greatness. BTW, started my own online clothing store not long ago - pretty cool, huh? Jon : Thanks, Gina! Appreciate your support. Your store looks great, remember it! Gina : Thanks, Jon! After losing my job, wanted to take control of my own destiny seemed like perfect way to do it. tough journey, but very rewarding. Jon : Wow, you ' re awesome for going for it! Setbacks can help us reach our potential? having trouble with my business project. Any advice on staying motivated even when times are tough? Gina : Yeah Jon! Challenges awesome for learning and growth. To stay motivated, think of big goal and why I ' m doing it. get help from people who support me. dance it out. need advice on anything in particular? Jon : been feeling low on confidence lately. hard to run a business when don ' t have faith in yourself. tips on how stay confident in your business? Gina : I get it, Jon. Confidence important in business. stay motivated by reminding myself of my successes and progress helps to have good support system. focus on why you started this because you love it! Have faith in yourself, Jon. I do! Jon : Thanks! Your words mean a lot. focus on success and why I started. You ' re right, love it ll keep my confidence up. Gina : No worries, Jon! Sounds like what I said was helpful. incredibly talented and passionate about dance.Don ' t forget, believe in yourself abilities. Tackle obstacle keep shining! Jon : Thanks! Your support means a lot. gonna keep going reach dreams no. Gina : Go for it, Jon! You got this! Don ' t let anything stop you. We ' re in this together! Jon : Appreciate encouragement. keep pushing each other on this path. Gina : Yeah! Let ' s keep each other going. We can do it",
    "Jon : Hi! Since we last spoke still working on dance studio things looking up! Gina : Hi! You inspiring taking it on opening your own studio! Jon : Thanks! Losing my job gave me push to finally start my dream business : my own dance studio! Now ' stepping into unknown hoping for best. Gina : must be scary stepping into unknown but know you can do it, Jon. With your determination and drive, your dance studio will huge success. Keep positive outlook keep going! Jon : Thanks! It ' s bit scary, but think about my love for dance how it makes me feel. s been my stress - buster since childhood! Gina : Gotcha, Jon! Dance is my stress fix too. soon start all worries vanish. amazing what we can do for our own mental health with something we enjoy. Jon : Yeah, Gina! Dancing helps me de - stress. ' s where I ' m most alive. must - have in my life. Gina : I get it, Jon. Dance is just me - - can ' t picture life without it. s like air. Jon :! Dancing is like second nature to me. living my dream by having my own dance studio teaching others. Gina : living dream inspiring others too! Your studio will change things for lots of folks. Jon : hope so, Gina. want to create a place for people to dance express themselves - s been dream of mine. Gina : great dream, Jon! Giving people place to express themselves with dance important. Your studio make huge difference. Can ' t wait to see it happen! Jon : Thanks! Your help means a lot. Keep you posted on dance studio progress. Gina : Thanks! appreciate you keeping me in loop on this cool project. Can ' t wait to hear more watch it come to life!, btw, had interview for a design internship yesterday! was so cool.Jon : Wow, Gina, stoked about this! Taking risk is scary sure following my dreams will pay off in end. How did interview go? Gina : It was great! Jon : Glad to hear it. Been practicing dance routines lately keeps mind focused motivated. Gina : Wow! ' great. Dancing awesome for staying focused. Wanna show me a routine sometime? Jon : Sure, Gina! Wanna see one of my routines? Lemme know when got time send you a vid. Gina : Yeah, Jon, watch your routine! proud of you! Jon : Thanks a lot! Your help means a lot. get video to you soon! Gina : No prob! Always here to help. Can ' t wait to see the vid",
    "Gina : Hey Jon! Long time no talk! A lot ' s happened - accepted for fashion internship! Jon : Congrats, Gina! awesome news about fashion internship. stoked for you. Where is internship and how ' re you feelin ' about it? Gina : Thanks! ' excited and kinda nervous. Gonna be big change. part - time position in fashion department of an international company. Jon : Way to go, Gina! You stepped up. What ' s your plan for future? Gina : Thanks! mix of excited and scared to get into fashion, but trying to stay upbeat and learn as much as can. What about you? Got something new? Jon : currently reading \" The Lean Startup \" hoping ll give me tips for my biz. Gina : sounds great! Could it spark any ideas for your dance studio? Jon : book got me thinking about building a focused efficient business. Adapting and tweaking from customer feedback important, gonna try it out! Gina : Woah, Jon, whiteboard ' s got bunch of good ideas! How keep track and stay on schedule with dates? Jon : Thanks, Gina! helps me keep track of ideas and milestones. Gives me visual of my progress and keeps me organized. Gina : Nice idea! Having something visual can help with organizing and motivation. What ' re you working on currently? Jon : wrapping up business plan looking for investors. passion for project and belief in success are driving me. Gina : Wow, Jon! Impressed by your commitment. How ' s hunt for investors going? Jon : Thanks! Searching for investors tough, but staying hopeful. s all a process learning a ton. Gina : Yeah Jon, got right attitude! Keep learning and growing through it all. Keep going! Jon : Thanks! appreciate your help. keep on going and never quit. Gina : Keep it up! Jon : Thanks! Your words mean a lot.Don ' t worry, won ' t let anything get me down. Gina : Go Jon! Obstacles inevitable can do awesome things Keep going",
    "Jon : Hey Gina, thanks for being there for me believing in me. It means a lot. Gina : Sure, Jon! I ' m always around for you. How ' ve you been since we caught up? Jon : prepping for my dance studio more than ever! Gina : Proud of you for starting your own business! takes strength to stay hopeful. What doing to prep for your dance studio? developed video presentation to teach to style my fashion pieces, btw. Jon : Thanks, Gina! inspiring to work with young dancers, seeing passion commitment. Opening the dance studio ' s great experience - want it to be place of support and encouragement for all dancers. show me this presentation? Gina : Shure, will send it to you later. Starting this studio isn ' t just a business, place for dancers to grow. What support you offering them? Jon : Besides dance classes workshops offering one - on - one mentoring and training to help dancers reach full potential. Gina : Your one - on - one mentoring training will push dancers to reach goals. I get it had a mentor when learning how to dance. Jon : a mentor can do wonders. Guidance and support can help dancers shine. Gina : Nice one, Jon! How ' been using it? Jon : using it to stay organized and motivated. sets goals tracks my achievements helps me find areas to improve. Gina : cool system! Being organized sure is key for getting stuff done. keep up with your goals and progress? Jon : use whiteboard to stay on track visualize goals tokenize successes keeps me motivated and focused. Gina : Cool! using different colors? Jon : Yes. color - code achievements can easily track my progress stay motivated. Gina : color - coding great way to track your progress & stay motivated. Keep it up! Jon : Thanks! helps me stay motivated reminds me why I ' m doing this.Gina : Yeah, great idea! Jon : Thanks! Gina : Remember staying positive important. Rock on! Jon : Thanks, Gina! Your support ' s awesome. Gina : Thanks! Keep going for dreams don ' t quit! Jon : won ' t give up, Gina! ' ll keep pushing working to make dreams happen. Thanks for support",
    "Jon : Gina, won ' t believe it - got mentored by this amazing business dude yesterday! inspiring now m more pumped to chase my dreams. What ' s been up with you lately? Gina : Wow, Jon! Mentors can help. working on my online store, growing customer base. ' tough but determined. How about you? Any new things happening? Jon : Been doing promotion for my business. Crazy ride so far, hanging in there. any tips for marketing? Gina : Awesome! Marketing is key. Use social media channels work with influencers for bigger reach. Jon : Thanks for advice, Gina! started doing what said about social media posted dance videos creating a stir. Gina : Nice! Glad dance vids doing well online. Keep it up! Jon : Your help helps. thought about being an entrepreneur? Gina : Ha yeah, Jon. been one ' cause lost my job. opened an online clothing store s been great! Being my own boss doing something I love is awesome. Jon : Wow, Gina! You did great taking that leap. Congrats! any advice for someone just starting out? Gina : Thanks, Jon! huge jump, totally worth it. advice : stay passionate, focused and resilient. Challenges will come, believe in yourself keep going. stay open to learning improving. Jon : Appreciate your advice. stay resilient and focused key! Gina : Yep Jon, staying resilient and focused is key for any entrepreneur. Keep going don ' t give up! You got this! Jon : Thanks! won ' t quit, no matter. Your encouragement motivates me to keep going. Gina : Way to go, Jon! Don ' t quit, remember, failures lead you closer to success.Here ' s a pic from when I was dancing - tough road, but worth it! Jon : Wow awesome pic! You look great passionate about dancing. Reminds me I love performing. Thanks for sharing! Gina : Thanks! glad the pic reminded you of your love for dancing. Keep going after your dreams! Jon : Sure thing, Gina! Your help means a lot to me. not giving up. Gina : Go, Jon! I m here for you. Keep going! Jon : Knowing you ' ve got my back helps keep me going. won ' t let you down! Gina : No worries, Jon! inspiring with your determination passion for dance. Keep it up",
    "Jon : Hey Gina, hope you ' re doing great! Still working on my biz. Took short trip last week to Rome to clear my mind. Gina : Hi! Good for you! will help you to concentrate on your biz better. Jon : Thanks, Gina. Still working on opening a dance studio. Gina : When you opening the studio? Jon : official opening night is tomorrow. working hard to make everything right. Can ' t wait to see it all come together! Gina : Congrats, Jon! studio looks amazing. You put a lot of work into this pumped for launch tomorrow. Don ' t miss a beat! Jon : Thanks, Gina! excited! wild ride feeling good ready to give it my best. Gina : Wow, Jon, must be so excited! come so far since we last talked, tomorrow ' s gonna be a blast! long nights worth it - take time to savor it. Capture joy and thrill dance brings - s magical! Jon : Tomorrow ' s awesome night not gonna forget a second of it. put so much into this want to savor all good vibes. Thanks for always having my back. You ' re the best! Gina : always proud of you. Enjoy good feels tomorrow, you earned it! Jon : Thanks! Your pride and support mean a lot. Looking forward to enjoying the moment with you. Gina : ' ll be right by your side, Jon. live it up make great memories tomorrow. excited! Jon : Yeah! make awesome memories tomorrow at grand opening! Gina : Can ' t wait to make more memories at your dance studio! Jon : Looking forward to more cool memories! Gina : love being around friends having great time. Can ' t wait to have fun at your dance studio! Jon : Agreed! Gina : Can ' t wait for tomorrow ' s grand opening! Jon : Woohoo! Tomorrow ' s opening will much fun.Can ' t wait for it be there! Gina : Can ' t wait too! Jon : Definitely! make tomorrow unforgettable Gina. See you there! Bye! Gina : See you tomorrow. Bye",
    "Gina : Hey Jon, what ' s been up? cool stuff happened since we talked. acquired new unique pieces for my store. Jon : Congrats on your store, Gina! Happy for you! It looks sick - unique piece you ' re selling? Gina : Thanks! hoodie isn ' t for sale, from my own collection. made limited edition line last week to show off my style and creativity - tough but worth it! Jon : What gave you idea? Gina : design reminds me of grit takes to stand out face challenges. Jon : ' s awesome, Gina! Yesterday chose to go to networking events to make things happen. been tough but staying determined focused. Gina : Way to go, Jon! Attending networking events takes guts drive. Keep it up! Jon : Thanks! tough going since lost job investing time in business will pay off eventually. appreciate your help. Gina : No worries, Jon! You got this! know if need anything. Jon : Your help matters to me writing all plans down. Gina : Nice work! Tracking plans and goals is key. like picture of your progress. Jon : Thanks, Gina! Seeing goals written down on paper helps keep me motivated focused on what I have to do. know won ' t be easy, but ' sure it ' ll pay off. Thanks for support! Gina : No worries, Jon! When things get rough, keep persevering keep working hard. You ' ll get there! Don ' t quit! Jon : Thanks, Gina! sign reminds me to never give up, hard things get. I ' ll keep going! Gina : Believe in yourself keep going. You can do it! Jon : Thanks! feeling confident won ' t give up. Your support means a ton to me.",
    "Gina : Hey Jon! Long time no chat! How ' s the dance studio? Last week wild, noticed by fashion editors s been amazing but kinda scary. Everything ' exciting but lot of pressure to keep going up! Jon : Hey Gina! Congrats on fashion editors reach - out, awesome! Dance practice fun exhausting. stay determined make my own path by going full - time with my biz idea. Gina : remember sometimes stumbling blocks can be opened doors. Keep going! Jon : Thanks! Your support and encouragement means a lot. Losing my job was a bummer, pushed me to take plunge go for biz dreams. Started to learn marketing and analytics tools to push biz forward today. tricky, but ' m up for the challenge gonna make this work! Gina : Go get ' em, Jon! Jon : excited to guide and mentor aspiring dancers on dreams. Gina : Wow, Jon! awesome. Loving what you do bringing joy to others rewarding. You ' re perfect mentor & guide. Your positivity determination will make your dance studio a hit! Jon : Thanks, Gina - appreciate your words encouragement! Dance has power to bring us together create sweet moments. Moments like this remind me why chasing my dream keep me pushing through struggles. Gina : Take comfort in knowing solid community cheering you on, me included. Keep on pushing! Jon : Feeling supported by all of you means so much. gives me oomph to keep chasing my dreams. Your faith in me is priceless - won ' t let you down! Gina : Don ' t let anything stop you. You have potential! Jon : Thanks, Gina! Your faith in me is real boost. make my dreams come true! Gina : Keep pushing you ' ll get there. Your dreams are so close! Jon : Thanks, Gina! won ' t quit, even when it ' s hard.I ' m gonna make it! Gina : got this, Jon! Don ' t let bumps in road bring you down. Keep going make dreams reality! rooting for you! Jon : Thanks, Gina! belief in me means world. not gonna let anything stop me. ll keep pushing make dreams come true. Thanks for being great friend. You rock! Gina : Hey Jon, glad I could help! Always here to cheer you on. Jon : Thanks! Glad you are on my side. Gina : Sure, see ya. Bye! Jon : Bye! Gina :",
    "Gina : Hey Jon! Long time no talk! Last week built new website for customers to make orders. ' s been a wild ride but ' m loving it. What ' s up with you? How ' s the dance studio? Jon : Hey Gina, congrats on clothing store! dance studio is on tenuous grounds now staying positive. got temp job to help cover expenses while look for investors. It ' s tough, but sure ' ll be worth it. Gina : Thanks, Jon! Appreciate kind words. Sorry to hear about studio, glad to see positivity. Not easy facing setbacks but believe in you. Finding investors can be tough, passion and experience to make it happen. Rome wasn ' t built in a day keep pushing on! Jon : Thanks for support. Running a business isn ' t easy, but determined to make it work. How tackled challenges in your business? Got any advice? Gina : had tough times with my business, Jon. Sourcing trendy pieces for my store was big hurdle. had to do lot of research and networking. My advice? Don ' t be scared to reach out to people in your field for help and contacts. Networking was lifesaver for me opened me up to amazing products not have found otherwise. Jon : Awesome advice! Lately been networking s gotten me good stuff. can ' t beat what connections can do. Check this pic from last networking event! Gina : Nice one, Jon! Networking pays off. Connecting with like - minded people is key. How was event? Jon : Thanks! event was awesome met investors got good advice. energy motivating gave me boost to go after goals. Gina : Wow, Jon! Congrats on successful night! What are your plans now with advice you got? Jon : Taking your advice, sprucing up my biz plan and tweaking pitch to investors.working on online platform to show off dance studio ' s stuff. Gina : Sounds like great plan, Jon! online platform can show off your studio get investors. Need help with anything? Jon : Thanks, Gina! Appreciate offer. Need help with marketing strategies - advice on reaching target audience and raising awareness for dance studio? Gina : Yeah Jon, marketing is key for getting your dance studio noticed. Instagram and TikTok can help reach younger crowd. Posting dance clips or content related to dance can help. collaborate with local influencers or dance communities. help you with making content or managing your accounts. Jon : Sounds great. appreciate your help with making content managing social media. Let get together make the dance studio look awesome! Gina : create cool content manage social media accounts. Jon : Thanks for support. You rock! Gina : Thanks, Jon! You re awesome. Let ' s get to work and make your studio shine! Jon : Definitely, Gina! make our collaboration awesome bring dance magic to world. Can ' t wait to see what we can do together! Gina : Definitely, Jon! pumped to collaborate with you make sweet moves. Together can make a difference show the world what we can do. Let ' s go for it! Jon : Yeah, Gina! rock the dance floor teach others to chase their dreams. Let ' s go for it make an impact! Gina : Yeah Jon! make a difference show ' em what we got. can do amazing things together! Jon : Thanks for having my back.",
    "Jon : Hey Gina! haven ' t talked in few days. rehearsing hard working on business plans stressful dancing kept me going. Gina : Hey Jon! Remember, do it! should get to point where anyone else would quit not to stop there. No what you waiting for? Do it! do it! Jon : Ha, ha! Thanks, Gina. Sounds familiar, who do words belong to? Gina : It ' s Shia Labeouf! Jon : Ahhahha, really!? Yea definitely him. Gina : Hah, yeah! ) creative space for dancers important. Last Friday at dance class with group of friends felt it Your studio go - to spot for self - expression. Keep up good work don ' t forget passion for dance. Jon : Thanks, Gina! Your words of encouragement keep me motivated. Can ' t wait ' til studio starts welcoming dancers of all ages backgrounds! Gina : happy to see my words motivating you, Jon. < 3 Jon : Thanks a ton, Gina! Your help encouragement mean a lot. support will help me make it happen. Gina : welcome, Jon! here to support you. Every step s getting you closer to your dream. Never give up! doing great. Jon : Thanks, Gina! won ' t quit. gonna keep going, whatever comes my way. Gina : Remember Jon, Just do it! Jon : Ah ha ha, yeah, JUST DOING IT! Gina : That ' s the spirit! Bye"
  ]
}