{
  "version": 1,
  "use_ep": true,
  "compress_rate": 0.65,
  "context_map": {
    "entities": {
      "Deborah": {
        "type": "person",
        "count": 30,
        "last_session": 30
      },
      "Jolene": {
        "type": "person",
        "count": 30,
        "last_session": 30
      },
      "Deborah's mom": {
        "type": "person",
        "count": 5,
        "last_session": 30
      },
      "Seraphim": {
        "type": "other",
        "count": 4,
        "last_session": 28
      },
      "Anna": {
        "type": "person",
        "count": 6,
        "last_session": 19
      },
      "Friday": {
        "type": "date",
        "count": 4,
        "last_session": 29
      },
      "last month": {
        "type": "date",
        "count": 2,
        "last_session": 23
      },
      "a special bench": {
        "type": "place",
        "count": 1,
        "last_session": 19
      },
      "my mom": {
        "type": "person",
        "count": 1,
        "last_session": 19
      },
      "Battlefield 1": {
        "type": "other",
        "count": 1,
        "last_session": 20
      },
      "mom": {
        "type": "person",
        "count": 1,
        "last_session": 20
      },
      "last week": {
        "type": "date",
        "count": 2,
        "last_session": 24
      },
      "yoga retreat": {
        "type": "event",
        "count": 2,
        "last_session": 30
      },
      "mom's place": {
        "type": "place",
        "count": 1,
        "last_session": 21
      },
      "virtual conference": {
        "type": "event",
        "count": 1,
        "last_session": 21
      },
      "Jolene's partner": {
        "type": "person",
        "count": 2,
        "last_session": 30
      },
      "Jolene's mom": {
        "type": "person",
        "count": 1,
        "last_session": 22
      },
      "Jolene's partner's dad": {
        "type": "person",
        "count": 1,
        "last_session": 22
      },
      "Luna": {
        "type": "person",
        "count": 1,
        "last_session": 22
      },
      "Max": {
        "type": "person",
        "count": 1,
        "last_session": 22
      },
      "Engineering": {
        "type": "other",
        "count": 1,
        "last_session": 22
      },
      "meditation retreat": {
        "type": "other",
        "count": 2,
        "last_session": 27
      },
      "yoga": {
        "type": "other",
        "count": 1,
        "last_session": 22
      },
      "solar energy": {
        "type": "other",
        "count": 1,
        "last_session": 22
      },
      "clean water project": {
        "type": "other",
        "count": 1,
        "last_session": 22
      },
      "environmental issues": {
        "type": "other",
        "count": 1,
        "last_session": 22
      },
      "8": {
        "type": "number",
        "count": 1,
        "last_session": 22
      },
      "5": {
        "type": "number",
        "count": 1,
        "last_session": 22
      },
      "Rio de Janeiro": {
        "type": "place",
        "count": 1,
        "last_session": 23
      },
      "three years ago": {
        "type": "date",
        "count": 1,
        "last_session": 23
      },
      "Monster Hunter: World": {
        "type": "other",
        "count": 1,
        "last_session": 24
      },
      "last Friday": {
        "type": "date",
        "count": 1,
        "last_session": 24
      },
      "The beach": {
        "type": "place",
        "count": 1,
        "last_session": 24
      },
      "This month": {
        "type": "date",
        "count": 1,
        "last_session": 24
      },
      "lake": {
        "type": "place",
        "count": 1,
        "last_session": 25
      },
      "beach": {
        "type": "place",
        "count": 1,
        "last_session": 25
      },
      "Monday": {
        "type": "date",
        "count": 1,
        "last_session": 26
      },
      "Wednesday at 4": {
        "type": "date",
        "count": 1,
        "last_session": 26
      },
      "Friday at 5": {
        "type": "date",
        "count": 1,
        "last_session": 26
      },
      "yoga getaway": {
        "type": "event",
        "count": 1,
        "last_session": 26
      },
      "cafe": {
        "type": "place",
        "count": 1,
        "last_session": 26
      },
      "camping trip": {
        "type": "event",
        "count": 1,
        "last_session": 26
      },
      "Phuket": {
        "type": "place",
        "count": 1,
        "last_session": 27
      },
      "engineering studies": {
        "type": "other",
        "count": 1,
        "last_session": 27
      },
      "game": {
        "type": "other",
        "count": 1,
        "last_session": 27
      },
      "cats": {
        "type": "other",
        "count": 1,
        "last_session": 27
      },
      "Susie": {
        "type": "person",
        "count": 1,
        "last_session": 28
      },
      "Thailand": {
        "type": "place",
        "count": 1,
        "last_session": 28
      },
      "Sunday": {
        "type": "date",
        "count": 1,
        "last_session": 29
      },
      "festival": {
        "type": "other",
        "count": 1,
        "last_session": 30
      },
      "spring": {
        "type": "date",
        "count": 1,
        "last_session": 30
      }
    },
    "decisions": [
      "Jolene is trying to add workouts into her studying schedule",
      "Jolene and her partner enjoy gaming together",
      "Deborah organizes workshops and events for mindfulness and self-care",
      "Deborah takes her pets (cats) for a run in the park every morning and evening",
      "Jolene has a pet snake",
      "Deborah started a project for a cleanup in the community",
      "Jolene adopted Susie two years ago",
      "Jolene prioritizes self-care such as yoga and meditation",
      "Deborah made a meditation guide for her yoga retreat",
      "Jolene designed notebooks inspired by space and engines",
      "Jolene is working on a prototype to revolutionize aerial surveillance",
      "Jolene aims to devise a more productive and affordable aerial surveillance system",
      "Jolene has been trying out some time management strategies and using a bullet journal",
      "Jolene is interested in destressing and trying mindfulness",
      "Jolene bought a console for her partner on the 17th",
      "Deborah organized a yoga event last month",
      "Deborah used to play video games with her husband",
      "Deborah prefers to play detective games with her husband",
      "Deborah visited a place with lots of memories and brought flowers",
      "Jolene and Deborah decided to appreciate small things in life more",
      "Jolene is doing yoga and meditation to relax and stay focused",
      "Deborah practices yoga, meditation, and goes for walks to stay balanced",
      "Jolene has practiced yoga for 3 years to escape stress",
      "Jolene finds savasana pose helpful to relax",
      "Jolene has a goal to be successful in her field and make a positive impact",
      "Jolene is focusing on studying and gaining more experience",
      "Jolene is thinking about pursuing more internships",
      "Jolene and her partner engaged in a conversation about their loved ones' influence.",
      "Jolene wants to incorporate perseverance and resilience into her engineering projects.",
      "Jolene aims to work on renewable energy and clean water projects.",
      "Jolene and her partner plan to attend a meditation retreat.",
      "Deborah took Max when her mother passed away.",
      "Deborah adopted Luna from a shelter.",
      "Jolene and her partner took a trip to Rio de Janeiro",
      "They checked out yoga classes in Rio de Janeiro",
      "Deborah visited her mom's house last month",
      "Jolene meditates by a nearby tranquil spot to relieve stress",
      "Jolene and her partner visited an old temple in Rio de Janeiro",
      "Jolene has a new plant to nurture herself and embrace fresh starts",
      "Deborah attended a community meetup last Friday to share stories and connect with others.",
      "Jolene has been focusing on studying and her relationship.",
      "Jolene and her partner have been taking trips to the beach.",
      "Jolene has finals coming up and plans to take a trip afterward to relax and recharge.",
      "Jolene signed up for a meditation course at a retreat near a lake",
      "Deborah has made meditation part of her routine",
      "Deborah and Jolene decided to have a coffee date next Friday at 5",
      "Jolene decided to incorporate relaxation, self-care, and balance in life alongside engineering studies",
      "Jolene chose to practice mindfulness and gratitude",
      "Deborah reconnected with her mom's old friends",
      "Deborah shared stories and photos with her mom's friends",
      "Deborah got married on the special beach",
      "Deborah discovered her love for surfing on the special beach",
      "Deborah practices yoga on the beach for relaxation",
      "Jolene creates a serene yoga space with candles and oils",
      "Jolene and Deborah share similar meditation practices",
      "Jolene relaxes in her room",
      "Jolene has had Susie for two years",
      "Deborah and her neighbor ran a free gardening class for the community",
      "Jolene tried a scuba diving lesson last Friday",
      "Deborah visited her mom's old house last Sunday",
      "Jolene and Deborah decided to try surfing together",
      "Jolene and Deborah plan to go surfing next month",
      "Deborah attended a music festival with friends",
      "Jolene went on a trip with her partner",
      "Jolene and her partner participated in a yoga retreat",
      "Jolene is planning to get out in nature again next month"
    ],
    "timeline": [
      {
        "time": "Next month",
        "event": "Jolene plans to reconnect with nature"
      }
    ],
    "session_counter": 30,
    "token_budget": 300
  },
  "segments": [
    "Deborah : Hey Jolene, nice to meet you! How ' s your week going? Anything fun happened? Jolene : Hi Deb! Good to meet you! Yeah my week ' s been busy. finished an electrical engineering project last week - took lot of work it ' s done now. Anything fun happening for you? Deborah : Congrats! Last week visited a place holds memories for me my mother s old house. Jolene : Why does it hold such special memories for you? Deborah : full of memories, she passed away few years ago. our last photo together. Jolene : Sorry about your loss, Deb. My mother also passed away last year. my room in her house have many memories there. anything special about it you remember? Deborah : My mom ' s house had special bench near the window. She loved to sit there every morning take in view. come to sit here sometimes helps me stay connected to her. Jolene : Staying connected important. something to remember her by? pendant reminds me of my mother gave it to me in 2010 in Paris. Deborah : Yes, also have a pendant reminds me of my mother. what special for you about your jewelry? Jolene : has special symbol represents freedom for me nice reminder to go for my goals not get held back. Deborah : should give you strength and energy! Jolene : have goals? Deborah : goals is to keep teaching yoga supporting my community. passionate about helping people find peace and joy through. Jolene : inspired you to go down this route? Deborah : Yoga helped me find peace during rough time now passionate about sharing that with others. Jolene : truly inspiring! Deborah : Gotta run, bye! Jolene : Looking forward to next chat",
    "Deborah : Hey Jolene, sorry to tell you this but my dad passed away two days ago. ' s been tough on us all - his sudden death left us all kinda shell - shocked. trying to channel my grief by spending more time with family cherishing memories. moments remind me to live life fully. Jolene : Sorry to hear about your dad, Deborah. Losing parent is tough - how ' s it going for you and your family? Deborah : Even s hard comforting to look back on great memories. looked at the family album. Photos give me peace during difficult times. my parents ' wedding in 1993. Jolene : They beautiful couple! Deborah : My husband and I trying to be as good a family as my parents were! Jolene : What do you value in your relationship? Deborah : love, openness kept us close all these years. Being there for each other made us both happy. Look what letter received yesterday! Jolene : touching words! Who is this letter from? Deborah : group members sent this to me! thanked me for positive influence on. moments remind me why passionate about yoga. Jolene : Where do you most often do yoga? Deborah : one of places where I do it. Jolene : Where is it? Deborah : my old home. go there now then for my mom, who passed away. Sitting in spot by window gives me peace. Jolene : Must great to have place where feel connected to her. Deborah : s special. can feel her presence comforts me. Jolene : sounds spot holds sentimental value. bring back any special memories? Deborah : Yeah, Jolene. ' d sit there every night with book and smile, reading was one of her hobbies one of her favorite places in house. Jolene : What other hobbies did your mother have? Deborah : Travel was her great passion! Jolene : want to show you one of my snakes! They calm me down make me happy. This is SusieDeborah : Having a pet brightens up your life. ' s great it brings you comfort. any fun moments with your pet like to share? Jolene : playing video games my pet slinked out of her cage coiled up next to me - too funny! second snake Seraphim did it. Look at her sly eyes! Deborah : Awww so nice! Jolene : bought it a year ago in Paris. Deborah : Cool, Jolene! Pets bring much happiness! Jolene : very unusual pets! Here ' s me and my partner gaming last week - fun. played game \" Detroit \" on console. both crazy about this activity! Deborah : your boyfriend teach you to play? Jolene : Even as child learned to play on my own. Deborah : only play old games or try new ones? Jolene : planning to play \" Walking Dead \" next Saturday. Deborah : Take care and keep spreading good vibes! Jolene : Thanks, Deb! You too, take care. See ya",
    "Jolene : Hi Deb! How ' re you? I ' ve been busy. My engineering professor gave us a huge robotics project. It ' s tough but fun, making me get creative and problem - solve. Deborah : Hey Jolene! s great to hear from you. sounds challenging but interesting! must be putting your creative and problem - solving skills to test. How did you feel when you first received project? enjoying working on it? Jolene : When got it felt mix of emotions - excited and nervous. But now enjoying it! s like trying to solve a puzzle, figuring out best design and programming. Seeing robot come together is awesome too! Deborah : That ' s awesome, Jolene! enjoying process. must be satisfying to see it come together. Keep up good work! by met new neighbor Anna yesterday! Jolene : How did you two meet? Deborah : happened at yoga in the park. Jolene : Wow awesome! great connecting with people similar interests. Did you two talk about it? Deborah : Yeah talked about how it improved our lives sense of community it gives. Jolene : Sounds great! Deborah : thought about resuming yoga? Jolene :.. planned to play the console with my partner. Deborah : s also good that you have something to do together. Jolene : Thanks for kind words! Deborah : Gotta run bye! Jolene : See you soon",
    "Jolene : Hey Deborah! Good to hear from you. How ' ve you been? I ' been on an emotional rollercoaster lately, I ' m coping. Deborah : Hey Jolene! Good to hear from you. All good here - how about you? Anything new happening lately? Jolene : had major milestone last week it went well - relieved and proud. huge accomplishment for me as an engineer. Deborah : That ' s awesome. You must have worked hard for that. proud of you. Care to share more about it? Jolene : Thanks so much! had to plan and research a lot to design build a sustainable water purifier for rural community in need. tough, but loved the experience. Deborah : Your engineering skills made difference for people in rural area. That ' s amazing! How did it feel when saw it working? Jolene : surreal moment. Seeing working providing clean water to community was satisfying. reminded me of how engineering can make difference in people ' s lives. made me feel like I had a purpose had done something good. Deborah : what are your career aspirations now? Jolene : want to keep working in engineering continue make positive impact on communities in need by creating sustainable solutions. goal is to contribute towards making world better place with my work. Deborah : sure great things will keep coming your way. Keep up good work follow your passions! Jolene : Your support means a lot. determined to keep going make a difference. Your encouragement motivates me to pursue my passions. Deborah : When things get tough take deep breath remember why you ' re doing this. spend a of time, teaching yoga. great way to find balance reconnect with ourselves. bonded with Anna during yesterday ' s l yoga class. Jolene : Wow awesome! What new poses you try? Deborah : trying out different dance poses, like Warrior II, builds strength boosts focus.Jolene : difficult to do? Deborah : Yes, this brought us closer to Anna! supported each other, means a lot. Jolene : explain how to do it? Deborah : Sure! To do modified pose, sit on edge of a chair with your feet planted. Twist your torso to one side use hand on knee for support. ll feel a stretch in your back and shoulders as hold it for few breaths, then switch sides. great for relaxing tense muscles. Jolene : Sounds really hard! Here ' s my bookshelf! Deborah : s quite a collection! had favorite book lately? love to hear your thoughts. Jolene : Thanks Deborah! m into this book called \" Sapiens \" - fascinating look at human history and technology affected us. giving me a lot to think about! Deborah : Great, interesting! come across any recent ones that struck you? Jolene : Two weeks ago read \" Avalanche \" by Neal Stephenson in one sitting! Deborah : sounds cool, Jolene. Stories can be powerful - can teach us, motivate us, bring us together. Jolene : also read recent story about someone who became successful despite facing numerous challenges. showed me anything is possible if you believe and work hard. Deborah : powerful message. reminds me of someone special and their grace and strength when faced hardships. Check out this creation! Jolene : Wow, Deb! ' s beautiful! tell backstory of that bouquet? Deborah : My friend gave me this bouquet when was struggling, gives me hope and courage. filled with warmth and appreciation when look at it. Jolene : ' s really sweet. small thing can make a real difference. Deborah : amazing how something as simple as flowers can make a real difference. Nature sure is beautiful. Jolene : Where are some of your favorite nature spots? Deborah : so many great places! favorite is a park with forest trail - so calming getting lost in nature.Then there ' s this beach nearby I love - sound of waves and sand under my feet make me feel all peaceful happy. any favorite spots, Jolene? Jolene : Here ' s a picture I took on vacation last summer in Bogota. beautiful calming watching sunset over water. made me appreciate nature ' s calming power. Deborah : sounds great, Jolene. Nature ' s calming for sure. it helps us forget daily craziness find inner peace. No wonder you ' re a fan! I like to come to this spot by water near my mom ' s old house. I reflect on her life find peace. Being surrounded by nature helps a lot. Jolene : ' s so touching! any little traditions when to reflect on your mom? Deborah : remember this amulet from her? Whenever come here I bring it with me. s how I feel her love stay close to her. Holding it brings me comfort. Jolene : s amazing how something small can have big impact,? Deborah : even small things like this can make big difference. reminder of all love and strength we have inside, connecting us to people we ' ve lost comforting us. Jolene : can keep them close in our hearts every day. Deborah : Anna has a pendant she wears in memory of her mother! brought us closer. Jolene : s nice to have reminders as source of strength when we need it. Deborah : Life ' s tough but hang in there. Look to your sources of strength you ' ll do great. Stay in touch, take care of yourself, know always here to cheer you on! Jolene : Thanks, Deb! Your encouragement means a lot to me. I ll stay in touch. Bye, take care and keep shining! Deborah : Stay safe! Bye",
    "Jolene : Hey Deborah! Been few days since we last talked wanted to fill you in on something cool. Last Wednesday did a mini retreat to assess where I ' m at in life. dope experience gave me new outlook. Deborah : Hey Jolene! Sounds great. Taking time to reflect can be awesome. gain any new insights from? Jolene : achieved much more than imagined. real confidence boost. Deborah : deserve credit for stepping outside your comfort zone and believing in yourself. What cool stuff did you accomplish at retreat? Jolene : accomplished something with my engineering project - came up with neat solutions excited about it. Deborah : Let s go into more detail. Jolene : Green tech could make difference in disadvantaged areas. like to look into it see how I can contribute. speaking of helping out had idea : volunteer program where engineers teach STEM to underprivileged kids. What do think of that? Deborah : sounds great, Jolene! great way to help inspire others. They benefit a lot from your knowledge. Have thought of a plan yet? Jolene : Haven ' t finished planning yet but thinking of teaming up with local schools/centers to do workshops. could invite engineers as guest speakers to show kids career options. Deborah : Having guest speakers like them give kids real - world view. reached out to any schools or centers yet? Jolene : No, not yet. want to solidify the plan first. Can ' t wait to start reaching out,! Deborah : That makes sense. excited to hear how you reach out help those kids. Let me know how it goes! Jolene : I ' ll keep you posted! Appreciate the support! my sketches in planner. Deborah : Sounds like you ' re doing great. if need more tips or information. Jolene : Thanks, Deb! If need anything else ' ll let you know. You ' re awesome! Deborah : You ' re awesome too! Take care! Jolene : Stay safe",
    "Jolene : Hey Deborah, totally buzzing! Had great night out last night - dinner, drinks with friends. glad I got to let my hair down. You? Deborah : Sounds great, Jolene! visited this place was so calming. Nostalgic too. Jolene : Wow flowers are beautiful! What type are they? looks peaceful there. Deborah : roses and dahlias bring me peace. lost a friend last week been spending time in garden to find comfort. Jolene : Sorry to hear about your friend, Deb. Losing someone can be tough. How are you holding up? Deborah : Thanks for kind words. s been tough, but comforted by remembering our time together reminds me of special life. Jolene : Memories can give us much comfort and joy. Deborah : Memories keep loved ones close. last photo with Karlie taken last summer when we hiked. was our last one. had such great time! Every time I see it can ' t help but smile. Jolene : Wow looks like great trip! Where else have you traveled? Deborah : been blessed to travel to few places Bali last year was one of my favs. gorgeous island gave me peace, great for yoga. Jolene : Wow ' s great! Is yoga on the beach a thing? been wanting to try it. Deborah : sound of waves fresh air wonderful! Jolene : ' ll give it a go! sounds peaceful. Thanks! Deborah : Let me know how it goes. Enjoy it! Jolene : ll keep you posted if I decide to go there. Deborah : Take care",
    "Jolene : Hi Deborah, it ' s been a while! Since we last talked, so much has happened. Balancing engineering school with partner ' s video games is quite a feat. also setting aside time for myself, doing yoga and meditation. helps give me calm amidst craziness. Deborah : Hey Jolene! Great to hear from you. Taking a break is key. How have practices helping with everything? Jolene : They seriously saved me. I chill out gain perspective when I do yoga. Afterward more alert and motivated. my last photo. Deborah : Wow cool that yoga helping you out! Do they also do yoga with you? Does your partner do yoga with you? Jolene : He started joining me sometimes, nice for bonding and relaxing. brought us closer. just our random photo. Deborah : Aw s wonderful! How long you been married? Jolene : We re not married yet but been together for three years. taking it slow loving the ride. ring on his hand is just a decoration, not a wedding ring. Deborah : Sounds nice, Jolene. Enjoying journey main thing. how did you two meet? Jolene : met in engineering class in college quickly became friends. eventually blossomed into something more s been great! Deborah : your relationship started from strong friendship. still enjoy working on engineering project s together? Jolene : teaming up for these projects feels great! get each other ' s struggles both love it. Deborah : Have yoga or meditation helped with any stress? Jolene : Whenever overwhelmed take a break do some breathing or meditate. helps me feel calmer clearer to handle challenges more easily. Deborah : s been great to see your progress since we last chatted - keep it up! Jolene : Thanks, Deb! Your support means a lot. keep pushing forward continue taking time for myself. Deborah : Always rooting for youRemember to listen to your heart take good care. Here ' s a photo I took while reflecting outdoors. reminder to find peace even in chaos. Jolene : curious, what does your daily routine look like? Deborah : In morning meditate, do yoga teach classes. yesterday went for morning jog for first time in nearby park will now incorporate this into daily routine. in evenings spend time with loved ones. Jolene : Why you decide that? Deborah : Exercise is key for me - makes me feel connected to my body. Jolene : great healthy habit! Deborah : ' s like they say - \" Can ' t pour from empty cup. \" Looking out for ourselves gives us energy to help others. don ' t forget, you ' re worth it too! Jolene : Thanks, Deb. Your words mean something to me. keep remembering to prioritize self - care",
    "Deborah : Hey Jolene, Anna got me a vegan stir - fry other day - tofu veg with ginger soy sauce. It was really tasty! Food wonderful source of pleasure nourishment. What dishes comforting to you? Jolene : One of my favorite dishes is lasagna! Comfort food can be great pick - me - up. got a lot going on with my studies and exams. Deborah : to find time for yourself lately? Jolene : trying to squeeze in me - time. Last Friday, did yoga and meditation to relax. find time for yourself too? Deborah : also did same, helped me reset my mind. How does it make you feel? Jolene : amazing few quiet moments can work wonders for soul. Deborah : to get outside lately? Jolene : take Seraphim to park last Sunday. She loved it here ' s a pic. Deborah : Looks like you had fun! Jolene : explored new places. People surprised when see tamed snake. What like about being outdoors? Deborah :.. birds chirping breeze gently blowing! reminds me of what really matters. Jolene : like reminder to slow down appreciate little things. Deborah : anything want to be more mindful of now? Jolene : need to be more mindful of stress levels take care of mental health. Sometimes get too caught up in studies forget to prioritize self - care. Deborah : Life can get hectic easy to forget about ourselves. Jolene : Exams and deadlines got me feeling overwhelmed. look at my to - do list! seems never - ending... Trying my best but been challenging. Deborah : Your efforts will bear fruit, don ' t give up! Jolene : Thanks, Deb. Any tips on studying or time management? Deborah : tip is to break it into smaller pieces set goals for yourself.For time management planners or schedulers help stay organized give time for yourself. Let me know if need help with study plan! Jolene : appreciate your help. Deborah : Take care good luck with exams. ' ll give you a mug like this one! encourages. Jolene : Thanks, Deb! cheered me up. All best with your classes. Bye! Deborah : Thanks, Jolene! Glad bring a smile to your face. Take care sure give yourself time to relax. Bye!",
    "Deborah : Hi Jolene! We haven ' t corresponded for a long time! Jolene : Hey Deb, yeah life can get chaotic. How ' s it been going lately? Deborah : So much been going on lately. started yoga class in neighborhood - s good feeling! Now to share exercise with neighbors watch it transform them. Jolene : Congrats. How did you do this? Deborah : Thanks! neighbors interested in trying yoga hosted class for them on Friday. great to see everyone embrace enjoy it. Here is our photo together. Jolene : ' s cool! What made want to start teaching it? Deborah : find it calming wanted to share with others. Giving people peace and awareness brings me much happiness. Jolene : Wow, Deb! ' s awesome when can share something we love make things better for others. Deborah : Teaching it is awesome because can help others made great friends through it. nice for building community connections. Jolene : motivating. great to have support in tough times. Deborah : s one of life ' s best parts, right? Jolene : having someone to rely on is key in tough times. makes difference in how we handle life. Plus ' s something I wanted to tell you. Deborah : What ' s up? I ' m listening. We ' ll figure it out. Jolene : hard time dealing with Engineering assignments. a lot to manage struggling to keep up. Can still talk about time management? Deborah : Sure, Jolene. Let ' s find a time that works for both of us. Jolene : find time to chat - ll check my schedule get back to you. Deborah : Take your time, Jolene. ' ll work it out. Take care of yourself, OK? Jolene : ' ll make sure to take it. See you soon! Deborah : ' m here for you if you need me. ' s catch up soon. Jolene : Have a great day",
    "Deborah : Hey Jolene, it ' s been a while. Hope you ' re doing okay with all your exams and deadlines. know ' s difficult for you right now. Jolene : Hey Deb! Yeah can be tough. Trying to find time for everything is like playing catch - up - stressful! Deborah : How manage your time stay organized with all projects and deadlines? Jolene : using Pomodoro Technique - 25 minutes work, 5 - minute break - to avoid burnout but still struggling to prioritize. any other tips on time management? Deborah : create daily schedule or to - do list. s my example for today. Jolene : tried making one but overwhelming when big stack of tasks. example from last Friday. Deborah : tried breaking it down or prioritizing tasks? Jolene : can often feel overwhelming difficult to figure out where to start. Deborah : get it, Jolene. When overloaded, use certain method. helps me figure out what ' s important and urgent more organized. Do you know about it? Jolene : Nah not familiar with that one. What ' s it about? Deborah : Want me to tell you about it? helps you organize things based on how important and urgent. Jolene : Sure tell me more about it! sounds useful. Deborah : Eisenhower Matrix sorts tasks into four boxes, categorizing them based on urgency importance. can be useful for organizing prioritizing. ' a breakdown. Jolene : visualization is helpful too. Thanks for sharing! Deborah : glad, was helpful. s give it a try see if helps stay focused less stressed. Jolene : Yeah, ' ll give it a go. Fingers crossed it ' ll help me. Thanks for the help! Deborah : Don ' t forget to take it easy look after yourself. Wishing you all the best! Recently, Anna and I were sitting by the sea, watching sunset talking about each other. realized we inspire each other.thoughts does sea in this photo make you think of? Jolene : gets me thinking of when I ' ll learn to surf. Gotta find spare time! Deborah : Surfing, huh Jolene? Chase your dreams, don ' t be daunted. thought about steps can take? Jolene : Definitely! gathering information watching videos got beginners ' guide to surfing need to find right time place to get lesson. Deborah : Way to go! Taking first steps is key. Believe in yourself keep going! Jolene : Thanks for support! got me pumped to try surfing. keep pushing myself to make it happen. Deborah : Keep it up, Jolene! Remember, experience matters as much as end result. Step by step have fun along way. You can do it! Jolene : Thanks for boost",
    "Jolene : Hey Deb, long time no talk. A lot ' s happened! On Friday had breakthrough with my engineering project. Finally found solution to a prob s bugging me. Feels great to see my hard work paying off. Deborah : proven your skills. Feels great, right? Keep it up! bought new props for yoga class! Here it in action. Jolene : also have new details for this case! Rate it! Deborah : That s cool! bought this candle for atmosphere to improve yoga practice. How about you? When do it, what feelings do you get? Jolene : feel relaxed during this activity. love creating serene space with soothing scents like lavender and rosemary. any favorite scents or rituals for it? Deborah : also big fan of scents like this! Candles and essential oils add warmth and calm to yoga session s amazing certain smells can transport you to place of peace. any other ways to enhance yoga practice? Jolene : find music helps me. Any favorite tracks? Deborah : find instrumental tracks with mellow melodies and rhythms help create peaceful vibe. One of favorites is track called \" Savana. \" What songs / artists like listening to during your practice? Jolene : love listening to Nils Frahm and Olafur Arnalds during my practice. Their music calming puts me in different headspace. any recommendations for other similar artists or tracks should check out? Deborah : listening to album called ' Sleep, ' great for meditation and deep relaxation. Hope find it as calming as I do! Jolene : Thanks for the tips, Deborah! gonna check them out. always good to have new tunes for yoga! Deborah : Let me know your thoughts on albums! Jolene : See you! Deborah : Take care and keep up good work",
    "Deborah : Hey Jolene! Great to see you! Had blast biking nearby with my neighbor last week - freeing beautiful. Checked out art show with friend today - cool inspiring stuff. Reminded me of my mom. Jolene : Hey Deborah! Sounds like you had blast biking and at art show. Your photo looks like you were into it! make think profound thoughts? Deborah : My mom interested in art. believed art could give out strong emotions connect us. When I go to art show, ' s like we ' re still experiencing it together even though she ' s gone. hard but comforting. Jolene : Losing someone is hard, but finding something helps you cope is great. Deborah : Finding ways to keep her memory alive gives me peace. amazing something simple like artwork can bring back powerful emotions remind us of those we ' ve lost. about finding solace in things we love, art has done that for me. Jolene : Even my snakes can ' t chat or understand what I going through our time together is valuable teaches me to take time be in tune with myself. playing video games with my partner after long day great way for to relax. Deborah : Simple things can bring us most happiness. How activities helped you during tough times? Jolene : brings us closer together! Deborah : comfort can be helpful when times get tough. Jolene : been working on big project lately - tough cool to watch it take shape. Can ' t wait to see final result! Deborah : waiting to hear how everything turns out. Keep up good work! Jolene : Thanks Deb! Your support means a lot. ll keep you updated on progress of project. Deborah : Glad my support means a lot to you! ' ll always be here for you. Jolene : Take care! Deborah : Enjoy your day make time for things that bring you joy. See ya! Jolene : ' ll make sure to find time for that.Have a good one",
    "Jolene : Hey Deborah! Long time no talk - had lots of stuff going on. Remember tough engineering project? I finally wrapped that up last month. Look at result! Deborah : Jolene! Congrats on wrapping up your with it! You put in the work and it paid off. Jolene : proud of myself for sticking it out despite problems and finishing it. ' s big milestone. Deborah : Now you ' ve reached this big milestone, what do you have planned next? Jolene : I ' m interning at a well-known engineering firm. s great opportunity to test my skills gain real - world experience. These my new colleagues! Deborah : What ' s best part of it so far? Jolene : best part far to apply what I learned in school to real projects. s fulfilling to see my ideas come to life. Deborah : Mind if ask how internship impacted you? Jolene : had positive impact on my life. stoked my love of engineering encouraged me to keep striving for my dreams. Deborah : How it inspired you to keep striving for your dreams? Jolene : Hanging out with people who love what they do inspired me to stay focused keep working towards my goals. s shown me with dedication and effort, anything is possible. Deborah : to find good work - life balance during internship? Jolene : finding balance tough. been slogging away s hard to make time for my hobbies and chilling out. Deborah : considered taking breaks finding activities like yoga to help relax and unwind? might make a difference. Jolene : Yeah m trying to do it. s example of how spent yesterday morning, yoga on top of mount Talkeetna. Deborah : Nice job, Jolene! How long have you been doing yoga and meditation? looks like ' s helping you regroup and recharge. Jolene : ' ve been doing them sporadically for about 3 years now had real positive effect on me.Deborah : Has it benefited you in any way? found it helpful in difficult moments? Jolene : helped me with stress kept me centered. Deborah : Glad they ' ve been helpful for you! Jolene : No idea how I would ' ve survived without them! Deborah : my favorite studio always so calming. Jolene : wondering if any advice on calming mind breathing during yoga? Deborah : recommend practicing mindful breathing for yoga. Set aside few minutes each day to sit with eyes closed take deep breaths focus on how air feels entering leaving your body. Jolene : Thanks, Deborah! ll give it a try. Appreciate advice! Deborah : If need more tips or help let me know. Take care! Jolene : See you",
    "Deborah : Hey Jolene! How ' s it going? haven ' t talked in a while. ' been busy getting ready for yoga retreat with buddies. chance to hang out with people who think like me find peace and understanding. Sounds awesome! Jolene : Hey Deb! Been super hectic with internship and stuff. retreat sounds awesome, could use a break! Deborah : By tried new pose - Dancer Pose ( Natarajasana ). Rate, did I succeed? Jolene : You amazing as always! new photos of Seraphim in new aquarium I bought day before yesterday. Deborah : Where ' d you get it? always drawn to animals, they bring much joy. What ' s its story? Jolene : got her last year, she ' s a great pet. She always cheers me up brings sense of peace. Spending time with her is comforting. Deborah : Pets do make life more enjoyable bright. Jolene : thankful it ' s here. Plus s nice to have calm creature around. Deborah : How have things been besides that? Jolene : Things intense lately. pushing myself to succeed, sometimes feels overwhelming. determined to overcome obstacles achieve my goals. Deborah : Keep up hard work remember to relax too. Jolene : Thanks, Deborah! had big breakthrough with this project - exciting and rewarding! Deborah : Awesome, Jolene! glad your project worked out. Jolene : Stop talking about me tell me more about your retreat. Deborah : rather show you a photo. also new yoga pose tried. tree pose. Jolene : What ' s that statue in the picture? Deborah : s symbol of peace and enlightenment. Jolene : looks gorgeous! d love to visit a retreat like that. seems like ideal spot to find peace and refreshment. Deborah : ' s perfect for reflecting and getting centered. Jolene : could use some chill time like that. Sounds so peacefulDeborah : Yeah need peaceful time to relax. Jolene : Gotta run, have nice day! Deborah : See you",
    "Deborah : Hey Jolene! started running group with Anna - ' s awesome connecting with people who care about fitness! Jolene : Cool, Deb! Glad you found some people to get fit with. ' trying to add workouts into my studying schedule, tough but fun. How about you? Any challenges with running group? Deborah : Oh, I ' m having a blast with it! We help push each other during our runs, makes easier to stay motivated. have lot of my photos from this activity. Jolene : Deborah, ' s awesome! Being part of supportive group must be super motivating. Finding team ' s passionate about something makes huge difference. thinking about my own journey too. Deborah : Having people who can cheer you on and give you advice makes a difference. What it been like for you finding supportive folks? Jolene : Gaming ' s tough lately, but grateful I have someone who ' s also into it. My partner helps me stay focused on our goals. have lot of cute photos, want to share with you. Deborah : What like best about gaming together? Jolene : to tackle challenges shared experience. s always a blast when we ' re into same game and achieve something tough. great way to bond and get closer. Deborah : Woah cool! Gaming is good for strengthening relationships. you two have favorite game to play together? Jolene : love playing \" It takes two \" together! fun team - strategy game competitive. Plus great way for us to bond. any activities you like doing with people? Deborah : do running and yoga / meditation with others. Connecting with people and creating community is great. love organizing workshops and events to practice mindfulness and self - care. awesome way to have fun, build relationships, support each other ' s growth. Jolene : Sounds like great way to relax. What do your workshops and events involve? Deborah : involves various activities such as yoga, meditation, and self - reflection.They aim to cultivate self - awareness promote mental emotional well - being help individuals find inner peace. It ' s a space where people can connect, explore, grow. Jolene : Your events are awesome for helping people connect learn, so important. How has everything been going for you? Deborah : Thanks, Jolene! s great seeing everyone come together support each other. amazing to witness growth transformation through these workshops. honored to be a part of it. Jolene : Wow, Deb! can imagine rewarding must to create space for growth change. great to hear everything ' s going well. can always count on me for support! want to share a photo with you. Deborah : Thanks, Jolene! Your support means a lot to me. I ' m here for you too. By noticed your pet in picture. What made you decide to get a snake? Jolene : fascinated by reptiles, felt like perfect pet for me. Taking care of it calming, great way to connect with nature. Deborah : Glad you found something gives you peace calm. have favorite memory with \" it \" to share? Jolene : have lots of great memories, like our little ' snake adventure '. She got out spent hours searching, relieved when found her snuggling under the bed. showed how much I love her. Deborah : What was it like when found her? can imagine the relief! Jolene : Seeing her snuggled under the bed made me feel much love and gratitude. made me realize how important she is to me. Deborah : They bring much joy remind us of what ' s important. Jolene : Animals teach us a lot about love and gratitude, bring much joy. Deborah : haven ' t introduced you to my pets yet! don ' t like dogs, ' s why I have cats.Jolene : Looks like they ' re having a blast! How often you take them out? Deborah : Exercise and nature important to me make sure to take them out for a run in the park every morning and evening. Jolene : Wow Deb, that ' s great! love to experience that every day. Deborah : Nature helps me find peace every day - ' refreshing! Jolene : ' s a pity that my snakes don ' t run! love to do that more often. They motivate me together more fun. Deborah : s like hitting a reset button helps me put things into perspective gives me time to reflect. Jolene : Yeah I totally get it. love going for walks to take it all in. take photos like this Deborah : s amazing how nature has power to bring us peace and clarity. Jolene : photo captures peacefulness of a lake surrounded by trees. Deborah : Why choose that spot? looks so calm. Jolene : hidden gem! makes me feel peaceful tranquil. Deborah : Lucky you for having somewhere to relax and tune out! Jolene : We ' ll definitely go there together sometime! Deborah : need a timeout",
    "Deborah : Hey Jolene! Great news - started project for cleanup in our community trying to raise funds for. ' s amazing to see everyone come together to make a difference. How ' ve you been? Anything new going on? Jolene : Hey Debs! Congrats on your project for community! for me life ' s been a rollercoaster lately. Last week, had huge setback with my project. put in so much work it all crashed lost everything. SO frustrating and depressing. Deborah : Jolene, sorry to hear that. It must be tough. I ' m here for you if can do anything, let me know. anything ' s helping you cope? Jolene : Your support means a lot. Susie helps when times get tough. Pets great company. Video games nice distraction. Deborah : They can provide love and comfort, especially during tough times. How come to have Susie? Jolene : adopted her two years ago when feeling lonely wanted company. Deborah : That ' s great, Jolene! Animals have way of bringing us happiness. They understand us provide us with comfort. Plus having a pet teaches us responsibility. She came at perfect time - cherish moments with her find strength in her presence. Jolene : Thanks Deborah. Having her around shows me can stay strong find joy in small stuff. Deborah : Enjoying little things is key. little moments can give boost push us forward. How you taking care of yourself lately? Jolene : trying to prioritize self - care, like yoga and meditation. helps me stay balanced grounded. Deborah : If interested can suggest some routines for you to try. Jolene : always on lookout for new routines to mix things up. Deborah : In check out this great place for yoga. Jolene : This room looks perfect for it. any favorite routines can share? Deborah : One of favorite yoga routines is gentle flow all about breathing and grounding.helps me find my chill. send you tutorial video with poses This is me in process : ) Jolene : Wow! help you find your chill or improve concentration? Deborah : great way to find balance in tough times. Try it out let me know what you think! Jolene : Can ' t wait to try it out. Let ' s chat soon! Deborah : Let me know how it goes. Talk to you later! Jolene : ll practice and update you. Bye",
    "Deborah : Since we last spoke made meditation guide for yoga retreat. How about you? Jolene : stressed since lost work files. was overwhelmed... meditation kept me chill got clarity back, thank goodness. appreciate practice! Deborah : It ' s amazing how can give you peace and calm in times like. If need any support, let me know - we ' re in this together! Jolene : Appreciate your support! BTW, wanted to share this with you. Deborah : Your creativity is amazing! Jolene : Thanks, Deb! inspired by love for space and engines designed notebooks with elements like galaxies and circuitry. they turned out cool! Deborah : have knack for turning these into art. make me feel excited just by looking at them. Your creativity amazing! usually inspire your engineering projects too? Jolene : Seeing art and design gives me unique perspective on problems. Deborah : Got any neat projects or ideas pumped about? Jolene : Working on cool project now - prototype could revolutionize aerial surveillance. Can ' t wait to see results! Deborah : admire your ambition to make a difference. any specific plans or goals for this project? Jolene : aim is to devise more productive and affordable aerial surveillance system. ll help with responding to emergencies and monitoring environment. make world better, safer place. Deborah : love your commitment. Keep going! Jolene : Thanks, Deb! Your support means a lot. ' ll keep pushing doing best to make a difference. Deborah : You got this",
    "Jolene : Been thinking a lot about my plans lately, especially after checking in with my bf. It ' s been up and down! Some days feels like trying to juggle my engineering, relationship, growing as a person, don ' t know how to handle it all. How manage when it ' s too much? Deborah : Finding ways to restore balance is important. Taking time for yourself recognizing needs can make a difference. Jolene : Thanks, Deb! been trying out time management strategies recently started using a bullet journal. s helpful for tracking my tasks staying organized. Deborah : s great to hear it ' s been helping you out! Jolene : Not only does it help me stay on top of everything satisfying when I cross tasks off my list Here ' s a pic of my newest spread with one favorite quotes. Deborah : love this quote. uplifting. Does it motivate you when you see it? Jolene : like little reminder to stick to my goals never give up. Deborah : Gotcha! Visual reminders like this photo can be super motivating. Keep focusing on your goals, Jolene, don ' t give up! led a meditation yoga sessionto elderly at local care home last week during sunset. Nature can be helpful for finding peace. tried mindfulness too? Jolene : Haven ' t tried it yet, but keen to give it a shot. sounds peaceful. could use some of that calm in my life now interested in destressing trying mindfulness. Deborah : started with workshops and books now mindfulness is huge part of my life. Jolene : I ' ll look into some of it. Can ' t wait to get started! Deborah : s great, Jolene! so glad you ' re willing to try some mindfulness. can be helpful. know if need any help getting started - happy to assist you with your journey! Jolene : appreciate it. Deborah : We ' re in this together.Give me shout if need anything. Bye for now. Jolene : Thanks, ' ll hit you up if need anything Bye for now",
    "Deborah : Hey Jolene! Hope you ' re having a good one. Last Friday I told Anna the story of my life they were super kind about it. nice to have meaningful connection. How ' s mindfulness workshops and reading going? Need any help? Jolene : Life ' s been hella busy since we last talked. bought a console for my partner as gift on the 17th it ' s much fun, he managed to play it.! Engineering studies still going strong too. Balance key for me lately. How about you? What ' s been up? Deborah : Well done! As for me been focusing on teaching yoga spending time with community. Organizing yoga event last month was cool. Jolene : rewarding seeing everyone come together? Can tell me more about how you put it together? any tips for maintaining balance between hobbies and studies? Deborah : reached out to different nearby businesses and places to make it happen. had yoga, food stalls live music - amazing! for balancing hobbies and studies find helpful to prioritize manage my time effectively. Making schedule setting aside specific time for studying pursuing hobbies can long way in maintaining balance. Jolene : Wow, ' s awesome! Gonna make plan to manage my studies and hobbies. Say ever play video games? Deborah : used to play some video games, ' s been a while. s good way to relax after busy day. any game suggestions? ' s your favorite game? Jolene : few game recommendations. Zelda BOTW for Switch is awesome open - world game. Animal Crossing: New Horizons is calming and cute. for my favorite game s hard to choose just one! Deborah : Cool recs! check those out. What about your favorite memories of playing video games? Jolene : forgot to mention Overcooked 2 - this is good co - op game if into hilarious and chaotic cooking.My partner and I often play for bets! once won three large pizzas! Deborah : Reminds me of when I used to play games with my husband. We ' d take turns great way to bond make memories. Gaming can bring people closer, right? Jolene : Yeah, you re right! ' s your favorite game to play with that person? Deborah : prefer to play detective games together. Jolene : What other activities both enjoy doing together? Deborah : also enjoyed spending time outdoors exploring nature. always so refreshing to be outside soak up fresh air. Jolene : ' m big fan of being outside too! s so calming and refreshing. any special spots like to go to? Deborah : love going to this park near my house - it has a nice forest trail and a beach. peaceful spot where can do some yoga and reflect. a special bench holds special meaning to me. Jolene : Sounds lovely! Nature can be calming. What makes this bench special to you? Deborah : holds lot of special memories for me and my mom - come here chat about dreams and life. full of good moments. Jolene : awesome, Deborah! some of your favorite memories with your mom at this spot? looks super peaceful and pretty. Deborah : ll always cherish my memories with her at this spot. remember beautiful sunset watched together in silence - colors in sky special. Every time I go back feel much peace and gratitude for time I spent with her. Jolene : Places and moments like that can mean so much, s gift to find peace and gratitude in them. Deborah : thankful for all the time we had. Jolene : s important to cherish it.",
    "Jolene : Long time no talk! given new game for console last week, it is Battlefield 1. What ' s been up with you? Deborah : Hey Jolene! Good to hear from you. That s cool! Been thinking about few big mom ents lately - went to a place that held lot memories for me. Sat on a bench where we used to chat brought back emotions. Jolene : Mostly happy or bit of everything? Deborah : quite a mix, Jolene. felt nostalgia and longing grateful for memories. ' s amazing how a place can mean so much. brought these flowers there. Jolene : think she would like it? Deborah : Yeah my mom loved flowers. always made her happy. appreciated simple things in life. Jolene : Wow great photo! How did she show you to appreciate it? Deborah : By taking it slow seeing beauty in them finding joy. Jolene : Wow Deb, ' s awesome! should take time to enjoy that not let business of life cause us to miss out on good stuff. Deborah : Yeah, Jolene. Life can be busy often overlook small things matter. make effort to appreciate them more. Jolene : Yep Deb, slowing down enjoying simple mom ents can bring of balance and happiness. trying to do more yoga and meditation myself to help relax stay focused. any calming habits practice to feel balanced? Deborah : Yeah, same here, Jolene! Yoga and meditation help me find balance inner peace. Going out for walks staying mindful keep me grounded. take similar photos on walks. Jolene : Gorgeous! Going for a walk feeling peaceful must be amazing. Deborah : Moments like that ' ll always cherish. Jolene : calm and peaceful feeling is nice - great for recharging and thinking. Deborah : like a reboot for me. Jolene : Got it! like hitting the refresh button coming back even better.Deborah : What ' s your favorite yoga pose for some rest? Jolene : fan of savasana - aka corpse pose. calming helps me let go surrender. Deborah : Funny photo! How long been doing yoga? Jolene : Been doing it for 3 years. great way to escape studying work stress. Deborah : Wow, Jolene! Taking time to unwind is key seems just right for you! Jolene : finding my zen again! Deborah : Keep it up! Jolene : Thanks for your support, Deb! Deborah : Good luck with everything. Stay in touch",
    "Deborah : Hey Jolene! Good to hear from you! A lot ' s happened since we talked - last week I got to go to this yoga retreat near my mom's place. cool - to hang with nature to know myself. Definitely life - changing! how beautiful it was there! Jolene : Wow, Deb, sounds great! Glad you to connect with yourself and nature. my own way to relax. your thoughts on life now? Deborah : Life ' s been super meaningful lately. Nature and self - reflection helped me see how beautiful every mom ent is. We can grow and learn when we listen to ourselves. What ' s been up with you lately? Any insights or experiences? Jolene : Life ' s hectic making strides toward my goals. tough, but satisfying. Deborah : Can you tell me more about it and what you ' ve achieved? Jolene : My goal is to be successful in my field make positive impact. studying, attending workshops, networking to make it happen. Recently opportunity to present at a virtual conference received positive feedback. great experience confirmed ' m on right track. Deborah : You put your heart and soul into it. Must have been amazing having it go well. How it feel when people gave you positive feedback? Any ideas for what comes next? Jolene : thrilled to receive positive feedback! felt rewarding to know my efforts appreciated. now focusing on studying gaining more experience. thinking about more internships to enhance my skills. Exciting times! Hopefully more updates to share with soon. Deborah : Wow, Jolene! Way to go! super proud of all you ' ve achieved. if need any help. Onward! Jolene : Thanks, Deb! Your support means a lot to me. Deborah : No problem. You got this! Jolene : not giving up, just gonna keep pushing forward. Deborah : Reach for your goals don ' t forget to enjoy the journey. Jolene : Thanks, DebYour support means a lot. ' ll keep pushing forward remember to enjoy every step of way. Deborah : Come on! journey ' s important as destination. Take time for yourself find joy in. believe in you! Jolene : Yeah, you ' re right! take your advice find joy on way. Cheers for support! Deborah : Always by your side",
    "Deborah : Hey Jolene, we talked I been thinking about my mom ' s influence. Remembering those we love is important. Jolene : I understand, Deb. Remembering cherishing memories of our loved ones is important. comforting to know their influence still guides us. Last Friday, my partner and I talked about how our loved ones influenced us their values meant to us. emotional chat, made us feel closer showed us what really matters. Deborah : types of conversations help build relationships. Can you tell me more about values they have given you? Jolene : Definitely! Our loved ones taught us to persevere stay resilient, like my mom said to never give up, my partner ' s dad showed them to stay determined. Their values influenced us to pursue our goals, such as me with engineering and my partner with creative endeavors. Even they not here we both feel their values encouraging us along our paths. Deborah : wonderful to hear, Jolene! amazing how their values continue to guide you, even in their absence. sounds like you and your partner honoring their memory by pursuing your respective passions. you ever considered incorporating those values into your work? Jolene : Yeah, Deborah! been figuring out how to add these values into our projects. As engineering student, want to use my talents to do good help solve important problems. keen on coming up with new ideas making things more efficient to make world better place. Going further mom stressed value of helping others want to keep in mind for engineering projects. Deborah : When our work ties into our values becomes more meaningful. What goals or ideas for incorporating values into future projects? Jolene : In future, aiming to work on projects make real difference to communities. interested in sustainable initiatives developing innovative solutions for environmental issues. want to get involved with organizations that focus on social causes, using my skills to help out. about connecting my passion for engineering with commitment to making positive impact.Deborah : You ve got lot of amazing plans for future. Which projects you most interested in getting involved in? Jolene : keen on two projects in. One focused on developing renewable energy, like solar, to help communities reduce dependence on non - renewables. Deborah : Wow Jolene, inspiring! Jolene : other finding ways to supply clean water to those with limited access Both align with beliefs about sustainability and assisting those in need. still have much to figure out before beginning, m up for challenge. Deborah : Sounds great, Jolene! Research key to success. Little steps being up for challenges make you stronger. I ' m here for you. Connecting to yourself helps tackle any issue. photo reminds me of beauty of nature during yoga session. Jolene : helps with challenges, giving balance and strength. Any tips for staying relaxed while studying? Deborah : Taking breaks, doing stretching / yoga, or going for walk helpful. don ' t forget to get enough sleep take time for self - care. Finding balance between work and taking care of yourself important. self - care activities doing lately? Jolene : been into yoga and meditation lately. helps me recharge. Doing different poses relieves tension calms my mind. shared newfound love for yoga with partner, planning to go on a meditation retreat together to enhance our practice together. Deborah : Glad to hear yoga helping you rest and recharge. great for reflection and self - care. Do your snakes also enjoy it? Jolene : My snakes like watching me chill. she ' s great company always brings sense of calm. Deborah : Having a pet around calming feeling. can bring great sense of comfort. still have cats, Luna is sitting on left. Jolene : Aww ' s adorable! ' s second one ' s name? Deborah : Max! They bring lots of joy and peace to our homeJolene : How did you get them? Deborah : Max is my mother ' s cat I took him when mother passed away. Jolene : You ' re great for taming him. How did you get Luna? Deborah : I took Luna from shelter. Jolene : s wonderful you become their loving owner! Deborah : Yes love cats need home, love, care! Max is already old is 8 years old. Jolene : How old is Luna? Deborah : She younger, 5 years old. Jolene : proud of your action to tame these pets",
    "Jolene : Hey Deborah, how ' s it going? Guess what? Yesterday my partner and I got back from awesome trip to Rio de Janeiro - checked out cool yoga classes. Deborah : yoga pose looks great. cool experience for the two of you. What did trip teach you? Jolene : This country was awesome! showed me different kinds of yoga and backgrounds made me appreciate it more. visited delicious cafes! you ever been somewhere important to you? Deborah : last month visited my mom s house holds special place in my heart. My mom had good and bad times there, ' s still a symbol of her strength and love she shared with me. This is my husband in front of this house. Jolene : What was it like? Deborah : brought back fond memories as relaxed outside. Jolene : Sounds great! glad you have place to relax and find peace. Deborah : Thanks, Jolene. s special for me. How about you? place that helps you relax? Jolene : go to nearby place to meditate by tranquil spot. Deborah : Looks chill. effect of that? Jolene : helps me make sense of everything relieves stress. like a restart. Deborah : Cool, glad found a place to chill. need that occasionally. one of favorite spots to ponder and let things go. Jolene : Looks great! What made you pick that spot? Deborah : soothing vibes and nice views made it ideal for reflecting and letting go. Jolene : one more photo from Rio de Janeiro. went on many excursions there. Deborah : Wow stairs look cool! Where taken? Jolene : had great time visiting old temple. stairs were amazing! Deborah : exploring temples must have been incredible! Three years ago was also in Rio de Janeiro, took beautiful photo on one of excursions. Jolene : architecture and history of it all were interesting. liked places you visited there! Deborah : Exploring historical places and learning their stories is fun.great experience. want to share this photo with you. Jolene : By way what did that paper have written on it in photo? Deborah : written to me by a friend who unfortunately will never to support me. miss him here. quote says \" Let go of what no longer serves you. \" Jolene : ' m sorry! good reminder to stay focused let go of what no longer serves us. Remember quote in my notebook? also inspires me! Deborah : What other quotes give you strength? Jolene : came across this one while browsing hit home with me. great reminder to ditch negative stuff focus on growing being positive. Deborah : Surrounding ourselves with good stuff striving to improve is key. Jolene : Yep, Deborah! about creating good atmosphere to help grow improve. By have new plant. Deborah : What made you pick it? Jolene : got this as reminder to nurture myself embrace fresh starts. Deborah : Nice job, Jolene! Take care of yourself embrace new beginnings. Jolene : Thanks Deb! Will do. Good talking to you. Take care! Deborah : Have a great day",
    "Deborah : Hey Jolene, catching up. went to a cool event last week with aim to support each other - pretty inspiring. been connecting with anyone lately? Jolene : Hey Deb, great to hear from you! been focusing on studying my relationship with my partner. taking little trips to beach great way to relax. How about you, anything new going on? Deborah : was busy too - went to community meetup last Friday shared stories nice to feel how connected we are. made me think about important relationships. How about you, how are things going in that area? Jolene : thankful for my significant other now. great to have someone encouraging my goals! How are things with your friends and family? Any updates on that front? Deborah : Relationships with family and friends vital. My yoga pals been my second family - held each other up through a lot. other day found this old photo. when first started doing yoga. My mum was my biggest fan source of motivation. She ' d often come to my classes with me. Jolene : Our loved ones sure are supportive! When I was 10, my parents got me that start of passion for video games. Deborah : Cool that they shared that with you. Did you learn on your own or teach you? Jolene : taught myself, my dad was always supportive my mom would play games with me. Deborah : ' s awesome! Sounds like had lot of support from your parents. favorite game to play with mom? Jolene : One of favorites was \" Monster Hunter: World \". immersive story and open - world gaming amazing! Deborah : can be so freeing when get immersed in game like that. Jolene : Yeah! my way to de - stress take a break from life. Deborah : What ' s up this month? Anything fun happening for you? Jolene : Got a lot of finals coming up this month been studying real hard. been quite stressful, ll be worth it in the end.Thinking about taking trip somewhere to relax recharge afterward Deborah : Good luck with it! Let me know if anything I can do to assist you",
    "Jolene : Woohoo! signed up for meditation course at retreat near lake. Can ' t wait to share experience with partner learn new techniques. Sooo excited! Deborah : s awesome! looks calm in pic - hope enjoy your experience learn new techniques! Jolene : amazing how something easy can make big difference to our health! Deborah : s become part of my routine now. Can ' t imagine my life without it. Jolene : Yeah, same! helps me stay balanced during studies. Deborah : Glad to hear it, Jolene. How ' s project going? Jolene : tough but chugging along. Thanks! Deborah : strong for handling challenges. You ' ve got this! Jolene : Thanks, Deb! Your support means a lot. ll keep pushing forward. Deborah : No worries, Jolene. ' m here if need me. Take care of yourself don ' t forget to rest up. Jolene : What been doing lately? Deborah : recently saw wonderful sunrise again. Jolene : Glimpsing calms me. Taking beach walks relaxes me. Deborah : photo remind you of something? Jolene : shot like reminder of last beach getaway. chill and nice. Deborah : Glad it brought back good memories. Jolene : Maybe one day to watch sunrise together! Deborah : offer can ' t refuse! Jolene : Bye, Deb! See you later! Deborah : See ya! Stay safe catch you later. Bye",
    "Deborah : Hey Jolene, had tough week. Storm forced us to cancel our yoga getaway. Jolene : Sorry to hear about it. How are you feeling now? Deborah : I was bummed about it, doing better now. just a setback, found comfort in my work spending time at home. Reminds me to be grateful for little things. you? How ' s it going? Jolene : My partner and I plan a camping trip to connect with nature practice yoga. Deborah : can be both good and tough to plan activities with busy schedule - what strategies use? Jolene : routine helps me stay on top of everything need to schedule for classes studying personal time. Self - care activities like yoga meditation help me stay balanced relax. Deborah : love to learn more about how you do it. Jolene : can tell you about it if interested. took bit of experimenting helped me. Deborah : Sounds great! set up coffee date talk about it! Jolene : Wanna meet up at that cafe next Monday? try fresh pastries. Deborah : Sounds good, Jolene! When did have in mind? That cafe rocks. Jolene : How about Wednesday at 4? Can ' t wait to catch up over coffee! Deborah : pic looks peaceful. Reminded me of cool hidden coffee shop near me. Rate it! Jolene : Tell me more about it when we meet, maybe next time ll be there. Deborah : Sorry remembered already have plans for this day. Jolene : Now see when more convenient for me. Deborah : Thank you for understanding ' m waiting. Jolene : How about Friday at 5? need to sort out books from bookcase will be free. Deborah : Absolutely, let ' s do that! Can ' t wait for coffee date next week. See you then. Stay safe! Jolene : See ya soon, Deb! Be safe excited for our coffee date! Deborah : Maybe grab me interesting books",
    "Jolene : Hey Deb! sorry for late reply, been super busy. Last weekend my partner and I traveled to a meditation retreat for few weeks in Phuket. Amazing experience! Nature, reflection and break from engineering studies were awesome - helped me find inner peace. Deborah : d love to hear more about your reflections how they changed you. Jolene : At retreat, had time to reflect on what makes me happy. made me realize importance of incorporating relaxation, self - care balance in life alongside my engineering studies. beauty of nature inspiring and refreshing! Deborah : anything from retreat that stood out to you? Jolene : one session stood out was about releasing expectations judgments savoring present. strong reminder to not just dwell on finish line, but to appreciate journey. usually get too consumed with hitting my goals forget to appreciate the ride. Deborah : ve been thinking about this a lot, too. Life ' s full of small moments being grateful for those can boost our happiness. Jolene : agree! Sometimes get too focused on big stuff don ' t appreciate all tiny wins. Like feeling of sun or great cup of coffee - can be small but they make life much better. Trying to be more mindful grateful to take it all in now. Deborah : That ' s great, Jolene! Practicing mindfulness gratitude can change our day - to - day. different outlook can make little things in life joyful. Glad you ' re getting into it! Jolene : experiencing new level of joy and happiness! Deborah : wonderful to see your progress, excited to be on this journey with you! Jolene : Thanks, Deb! Appreciate your support. great we can do this together. Deborah : Having supportive community helps. can motivate and encourage each other! By the recently played a game. don ' t remember what it ' s called.This card game about cats, take cards one by one from a deck then can attack your opponent with them. We ' ll definitely play it with you! Jolene : look forward to meeting you and playing this game",
    "Deborah : Since speaking last, reconnected with my mom ' s old friends. Their stories made me tear up reminded me how lucky I am to have had her. Jolene : ' s great you could reconnect with them. Hearing stories about our loved ones can be tough but also comforting. Deborah : Hearing stories about my mom was emotional. was both happy and sad to hear things I hadn ' t heard before. mix of emotions, but comforting to reconnect with her friends. Jolene : can bring up range of emotions, s okay to feel mix of happiness and sadness. moments with her friends must ' ve been meaningful to. Deborah : Wow so special. glimpse into her life beyond what I knew. Through their eyes appreciate her more. Here I am and my mom. Jolene : looks like a blast! What did you and your mom ' s friends do on day? Deborah : reminisced and looked through her photos. sweet. Jolene : Looking at old photos must have been nostalgic! great could share experience with friends. amazing how photos and memories can give us deeper appreciation for people we love. Deborah : Pictures have way of bringing back memories making us appreciate special bond with our loved ones. remind me of strong love and amazing human relationships. like this one. Jolene : gorgeous pic! any special memories of beach or love surfing in general? Deborah : beach is super special to me. ' s where I got married and discovered my love for surfing. always filled with joy and peace. Jolene : pleasant memories. Deborah : another photo from my classes. Jolene : yoga pose looks amazing! it help you relax? Deborah : Doing this on beach is so peaceful - ocean, sand, and fresh air create super relaxing atmosphere. perfect way to take care of myself.Jolene : like to create my own serene yoga space with candles oils for extra chill vibes tried new style of meditation in Thailand - with flowers. Deborah : same for me! Jolene : find calm when I do yoga or meditate. use essential oils put on soft, soothing music in background to create peaceful atmosphere helps me chill out center myself. Deborah : ' s amazing how our environment can enhance our practice. Jolene : totally! surroundings can affect our mood much zen can get from our routine. Creating a place that feels safe chill is key. Deborah : looks comfy inviting! Where usually go to relax in your house? Jolene : In my room, usually relax feel at ease. After busy day ' s my little haven for peace and rest - perfect spot to relax recharge. Deborah : Sounds like your room does the job. awesome. Jolene : Here are my pals keeping me company. Deborah : ' s Susie or Seraphim? How long has he been hanging out with you? Jolene : It s Susie! ' ve had her for two years now. Deborah : awesome how pets can bring us comfort and peace when need it. Jolene : Susie is great companion. Deborah : love pets give is priceless. Jolene : Plus they make life brighter",
    "Deborah : Hey Jolene, excited to tell you! Yesterday, me and my neighbor ran a free gardening class for community, was awesome! People of any age joined in great thing to see. Jolene : Wow, Deborah, that ' s awesome! Keep up great work, here hoping for more events this in future! Deborah : Gardening is amazing. brings us together in cool way. awesome to share my love of plants help people take care of world., what about you? Anything new happened lately? Jolene : tried scuba diving lesson last Friday had awesome time! found cool dive spot we can explore together. Trying new things opens up world of adventure - maybe one day I ' ll be a certified diver. Anything fun going on with you? Deborah : sounds amazing, Jolene! interested in underwater life haven ' t had chance to try scuba diving yet. Recently spending time remembering my mom. Last Sunday visited her old house sat on a bench. comforting experience if feel her presence guide me remind me of her love. Jolene : Visiting your mom ' s old home sounds like it was really special. something special you remember about her? Deborah : Thanks, Jolene! special. My mom had big passion for cooking. She would make amazing meals for us, each one full of love and warmth. can still remember smell of her special dish would fill house bring us all together. Jolene : looks delicious, Deb! sweet how cooking with your mom brought everyone together. ' your best memory of cooking with her? Deborah : loved it when she would bake pineapple birthday cakes for me when was a kid. always made me feel so special. Jolene : No wonder it made you feel special. Deborah : Have you ever had something like that with someone close? Jolene : used to bake cookies with someone close to meDeborah : What ' s your favorite cookie to make? Jolene : warm, gooey chocolate and soft, buttery cookie are a match made in heaven. Deborah : want to eat this now. Jolene : Well look what I have here! Deborah : anything special about it or photo? Jolene : takes me to another world when I read it! Deborah : show you have big bookshelf too? Jolene : think not, like it! Deborah : Having a space like this important for escaping reality and relaxing with a book. any books that moved you? Jolene : My bathroom has aesthetic vibe. Once read self - discovery book resonated with me. Deborah : Wow! special book that speaks to you helps with self - discovery? s awesome. Plus having cozy nook to chill? my best one! Jolene : Sounds nice, Deb! cozy nook is a must! beach is great place for finding peace and relaxation. ever tried surfing? Deborah : Certainly! ' s confirmation. Jolene : How cool! never decided to try it. Deborah : ' s okay, maybe can try it together sometime! Jolene : already know what fate awaits me if I do this! Deborah : been interested in this or know nothing about it? Jolene : started learning, but haven ' t gone yet. Want to come with me sometime? Deborah : ' ll be an adventure! make it happen soon! Jolene : glad remains to agree and choose right time for both of us. Deborah : Can ' t wait. What day works for you? really excited! Jolene : plan for next month - check my schedule let you know. Can ' t wait",
    "Deborah : had great time at music festival with my pals! vibes unreal music was magical. freeing to dance bop around. Music brings us together helps us show our feelings. reminds me of my mom and her soothing voice when she ' d sing lullabies to me. Lucky to have those memories! Jolene : Wow, festivals sound so fun! Here ' s me and my partner at one last year - had awesome time! s my way of expressing myself getting away from stress of everyday life. got back from a trip with my partner - cool! Deborah : Wow gorgeous shot! looks tranquil serene. You two look happy together. Trips create awesome memories we can share. Where did you go on your trip what ' s something you ' ll never forget? Jolene : Thanks! had awesome yoga retreat. place was peaceful view during yoga amazing - sunrise lit up whole sky with bright colors. beautiful, made us feel alive grateful. Deborah : Wow, what a view! How did it make you feel? Jolene : amazing! Doing yoga with backdrop made me feel connected to nature and myself. felt incredibly peaceful and thankful. Deborah : Like s no wonder looking at such beauty can help us refocus connect with who we are. you ever experienced that? Jolene : remember taking a hike with my partner coming across waterfall oasis. Everything felt peaceful my worries disappeared. refreshing experience. Deborah : planning to experience it again soon? Jolene :! planning to get out in nature again next month. s to great reconnecting with it! Deborah : Enjoy it! photo made me think of gorgeous blossom tree from near my home. Every spring, was magical to watch it bloom. Jolene : That sounds magical! How watching tree bloom each spring? Deborah : like admiring nature ' s artwork.filled me with awe made me appreciate beauty of life. Even in tough times hope for growth. Jolene : This photo I took is great visual representation of that idea. reminds me I can keep growing through any obstacles. Deborah : captures resilience and strength. love how find inspiration in small things. Jolene : Thanks, Deborah! Appreciating small things is important. helps me remember even when times are tough s always something positive to hang onto. Deborah : s great habit. Thanks for reminding me! Jolene : Sure Deb, s great catching up. Keep on finding those beauties"
  ]
}